{"__symbolic":"module","version":4,"metadata":{"SliderComponent":{"__symbolic":"class","decorators":[{"__symbolic":"call","expression":{"__symbolic":"reference","module":"@angular/core","name":"Component","line":44,"character":1},"arguments":[{"exportAs":"kendoSlider","providers":[{"__symbolic":"reference","module":"@progress/kendo-angular-l10n","name":"LocalizationService","line":47,"character":8},{"provide":{"__symbolic":"reference","module":"@progress/kendo-angular-l10n","name":"L10N_PREFIX","line":48,"character":19},"useValue":"kendo.slider"},{"multi":true,"provide":{"__symbolic":"reference","module":"@angular/forms","name":"NG_VALUE_ACCESSOR","line":49,"character":32},"useExisting":{"__symbolic":"reference","name":"SliderComponent"}},{"provide":{"__symbolic":"reference","module":"@progress/kendo-angular-common","name":"KendoInput","line":50,"character":19},"useExisting":{"__symbolic":"reference","name":"SliderComponent"}}],"selector":"kendo-slider","template":"\n        <ng-container kendoSliderLocalizedMessages\n            i18n-increment=\"kendo.slider.increment|The title of the **Increase** button of the Slider.\"\n            increment=\"increment\"\n            i18n-decrement=\"kendo.slider.decrement|The title of the **Decrease** button of the Slider.\"\n            decrement=\"decrement\"\n            i18n-dragHandle=\"kendo.slider.dragHandle|The title of the drag handle of the Slider.\"\n            dragHandle=\"Drag\"\n        >\n\n        <div class=\"k-slider-wrap\" #wrap\n            [id]=\"focusableId\"\n            [class.k-slider-buttons]=\"showButtons\"\n            [class.k-slider-topleft]=\"tickPlacement === 'before'\"\n            [class.k-slider-bottomright]=\"tickPlacement === 'after'\"\n            [attr.tabindex]=\"(this.disabled ? undefined : tabIndex)\"\n            [kendoEventsOutsideAngular]=\"{ focus: handleFocus, blur: handleBlur, click: onWrapClick, keydown: onKeyDown }\"\n            >\n            <a\n                #decreaseButton\n                *ngIf=\"showButtons\"\n                class=\"k-button k-button-decrease\"\n                [title]=\"decrementMessage\"\n                [attr.aria-label]=\"decrementMessage\"\n            >\n                <span class=\"k-icon\"\n                    [class.k-i-arrow-w]=\"!vertical\"\n                    [class.k-i-arrow-s]=\"vertical\"\n                >\n                </span>\n            </a>\n            <a\n                *ngIf=\"showButtons\"\n                #increaseButton\n                class=\"k-button k-button-increase\"\n                [title]=\"incrementMessage\"\n                [attr.aria-label]=\"incrementMessage\"\n            >\n                <span class=\"k-icon\"\n                    [class.k-i-arrow-e]=\"!vertical\"\n                    [class.k-i-arrow-n]=\"vertical\"\n                >\n                </span>\n            </a>\n            <ul kendoSliderTicks\n                #ticks\n                *ngIf=\"tickPlacement !== 'none'\"\n                [tickTitle]=\"title\"\n                [vertical]=\"vertical\"\n                [step]=\"smallStep\"\n                [largeStep]=\"largeStep\"\n                [min]=\"min\"\n                [max]=\"max\"\n                [labelTemplate]=\"labelTemplate?.templateRef\"\n            >\n            </ul>\n        <div #track class=\"k-slider-track\">\n            <div #sliderSelection class=\"k-slider-selection\">\n            </div>\n                <a #draghandle\n                    [style.touch-action]=\"isDisabled ? '' : 'none'\"\n                    class=\"k-draghandle\"\n                    [title]=\"dragHandleMessage\"\n                    kendoDraggable\n                    (kendoPress)=\"ifEnabled(handleDragPress ,$event)\"\n                    (kendoDrag)=\"ifEnabled(onHandleDrag ,$event)\"\n                    (kendoRelease)=\"ifEnabled(onHandleRelease, $event)\"\n                ></a>\n            </div>\n\n            <kendo-resize-sensor (resize)=\"sizeComponent(false)\"></kendo-resize-sensor>\n        </div>\n  "}]}],"members":{"focusableId":[{"__symbolic":"property","decorators":[{"__symbolic":"call","expression":{"__symbolic":"reference","module":"@angular/core","name":"Input","line":132,"character":5}}]}],"incrementTitle":[{"__symbolic":"property","decorators":[{"__symbolic":"call","expression":{"__symbolic":"reference","module":"@angular/core","name":"Input","line":136,"character":5}}]}],"decrementTitle":[{"__symbolic":"property","decorators":[{"__symbolic":"call","expression":{"__symbolic":"reference","module":"@angular/core","name":"Input","line":140,"character":5}}]}],"showButtons":[{"__symbolic":"property","decorators":[{"__symbolic":"call","expression":{"__symbolic":"reference","module":"@angular/core","name":"Input","line":145,"character":5}}]}],"tickPlacement":[{"__symbolic":"property","decorators":[{"__symbolic":"call","expression":{"__symbolic":"reference","module":"@angular/core","name":"Input","line":155,"character":5}}]}],"title":[{"__symbolic":"property","decorators":[{"__symbolic":"call","expression":{"__symbolic":"reference","module":"@angular/core","name":"Input","line":161,"character":5}}]}],"dragHandleTitle":[{"__symbolic":"property","decorators":[{"__symbolic":"call","expression":{"__symbolic":"reference","module":"@angular/core","name":"Input","line":165,"character":5}}]}],"vertical":[{"__symbolic":"property","decorators":[{"__symbolic":"call","expression":{"__symbolic":"reference","module":"@angular/core","name":"Input","line":170,"character":5}}]}],"min":[{"__symbolic":"property","decorators":[{"__symbolic":"call","expression":{"__symbolic":"reference","module":"@angular/core","name":"Input","line":175,"character":5}}]}],"max":[{"__symbolic":"property","decorators":[{"__symbolic":"call","expression":{"__symbolic":"reference","module":"@angular/core","name":"Input","line":180,"character":5}}]}],"smallStep":[{"__symbolic":"property","decorators":[{"__symbolic":"call","expression":{"__symbolic":"reference","module":"@angular/core","name":"Input","line":185,"character":5}}]}],"largeStep":[{"__symbolic":"property","decorators":[{"__symbolic":"call","expression":{"__symbolic":"reference","module":"@angular/core","name":"Input","line":192,"character":5}}]}],"fixedTickWidth":[{"__symbolic":"property","decorators":[{"__symbolic":"call","expression":{"__symbolic":"reference","module":"@angular/core","name":"Input","line":199,"character":5}}]}],"disabled":[{"__symbolic":"property","decorators":[{"__symbolic":"call","expression":{"__symbolic":"reference","module":"@angular/core","name":"Input","line":203,"character":5}}]}],"readonly":[{"__symbolic":"property","decorators":[{"__symbolic":"call","expression":{"__symbolic":"reference","module":"@angular/core","name":"Input","line":208,"character":5}}]}],"value":[{"__symbolic":"property","decorators":[{"__symbolic":"call","expression":{"__symbolic":"reference","module":"@angular/core","name":"Input","line":213,"character":5}}]}],"tabindex":[{"__symbolic":"property","decorators":[{"__symbolic":"call","expression":{"__symbolic":"reference","module":"@angular/core","name":"Input","line":218,"character":5}}]}],"tabIndex":[{"__symbolic":"property","decorators":[{"__symbolic":"call","expression":{"__symbolic":"reference","module":"@angular/core","name":"Input","line":223,"character":5}}]}],"onFocus":[{"__symbolic":"property","decorators":[{"__symbolic":"call","expression":{"__symbolic":"reference","module":"@angular/core","name":"Output","line":234,"character":5},"arguments":["focus"]}]}],"onBlur":[{"__symbolic":"property","decorators":[{"__symbolic":"call","expression":{"__symbolic":"reference","module":"@angular/core","name":"Output","line":239,"character":5},"arguments":["blur"]}]}],"valueChange":[{"__symbolic":"property","decorators":[{"__symbolic":"call","expression":{"__symbolic":"reference","module":"@angular/core","name":"Output","line":244,"character":5}}]}],"wrapper":[{"__symbolic":"property","decorators":[{"__symbolic":"call","expression":{"__symbolic":"reference","module":"@angular/core","name":"ViewChild","line":246,"character":5},"arguments":["wrap"]}]}],"track":[{"__symbolic":"property","decorators":[{"__symbolic":"call","expression":{"__symbolic":"reference","module":"@angular/core","name":"ViewChild","line":247,"character":5},"arguments":["track"]}]}],"draghandle":[{"__symbolic":"property","decorators":[{"__symbolic":"call","expression":{"__symbolic":"reference","module":"@angular/core","name":"ViewChild","line":248,"character":5},"arguments":["draghandle"]}]}],"sliderSelection":[{"__symbolic":"property","decorators":[{"__symbolic":"call","expression":{"__symbolic":"reference","module":"@angular/core","name":"ViewChild","line":249,"character":5},"arguments":["sliderSelection"]}]}],"ticksContainer":[{"__symbolic":"property","decorators":[{"__symbolic":"call","expression":{"__symbolic":"reference","module":"@angular/core","name":"ViewChild","line":250,"character":5},"arguments":["ticks",{"read":{"__symbolic":"reference","module":"@angular/core","name":"ElementRef","line":250,"character":32}}]}]}],"ticks":[{"__symbolic":"property","decorators":[{"__symbolic":"call","expression":{"__symbolic":"reference","module":"@angular/core","name":"ViewChild","line":251,"character":5},"arguments":["ticks"]}]}],"decreaseButton":[{"__symbolic":"property","decorators":[{"__symbolic":"call","expression":{"__symbolic":"reference","module":"@angular/core","name":"ViewChild","line":252,"character":5},"arguments":["decreaseButton"]}]}],"increaseButton":[{"__symbolic":"property","decorators":[{"__symbolic":"call","expression":{"__symbolic":"reference","module":"@angular/core","name":"ViewChild","line":253,"character":5},"arguments":["increaseButton"]}]}],"labelTemplate":[{"__symbolic":"property","decorators":[{"__symbolic":"call","expression":{"__symbolic":"reference","module":"@angular/core","name":"ContentChild","line":255,"character":5},"arguments":[{"__symbolic":"reference","name":"LabelTemplateDirective"}]}]}],"direction":[{"__symbolic":"property","decorators":[{"__symbolic":"call","expression":{"__symbolic":"reference","module":"@angular/core","name":"HostBinding","line":258,"character":5},"arguments":["attr.dir"]}]}],"horizontalClass":[{"__symbolic":"property","decorators":[{"__symbolic":"call","expression":{"__symbolic":"reference","module":"@angular/core","name":"HostBinding","line":260,"character":5},"arguments":["class.k-slider-horizontal"]}]}],"verticalClass":[{"__symbolic":"property","decorators":[{"__symbolic":"call","expression":{"__symbolic":"reference","module":"@angular/core","name":"HostBinding","line":264,"character":5},"arguments":["class.k-slider-vertical"]}]}],"sliderClass":[{"__symbolic":"property","decorators":[{"__symbolic":"call","expression":{"__symbolic":"reference","module":"@angular/core","name":"HostBinding","line":268,"character":5},"arguments":["class.k-slider"]}]}],"transitionsClass":[{"__symbolic":"property","decorators":[{"__symbolic":"call","expression":{"__symbolic":"reference","module":"@angular/core","name":"HostBinding","line":272,"character":5},"arguments":["class.k-slider-transitions"]}]}],"widgetClass":[{"__symbolic":"property","decorators":[{"__symbolic":"call","expression":{"__symbolic":"reference","module":"@angular/core","name":"HostBinding","line":276,"character":5},"arguments":["class.k-widget"]}]}],"stateDefaultClass":[{"__symbolic":"property","decorators":[{"__symbolic":"call","expression":{"__symbolic":"reference","module":"@angular/core","name":"HostBinding","line":280,"character":5},"arguments":["class.k-state-default"]}]}],"disabledClass":[{"__symbolic":"property","decorators":[{"__symbolic":"call","expression":{"__symbolic":"reference","module":"@angular/core","name":"HostBinding","line":284,"character":5},"arguments":["class.k-state-disabled"]}]}],"ariaDisabled":[{"__symbolic":"property","decorators":[{"__symbolic":"call","expression":{"__symbolic":"reference","module":"@angular/core","name":"HostBinding","line":288,"character":5},"arguments":["attr.aria-disabled"]}]}],"ariaReadonly":[{"__symbolic":"property","decorators":[{"__symbolic":"call","expression":{"__symbolic":"reference","module":"@angular/core","name":"HostBinding","line":292,"character":5},"arguments":["attr.aria-readonly"]}]}],"ariaMin":[{"__symbolic":"property","decorators":[{"__symbolic":"call","expression":{"__symbolic":"reference","module":"@angular/core","name":"HostBinding","line":296,"character":5},"arguments":["attr.aria-valuemin"]}]}],"ariaMax":[{"__symbolic":"property","decorators":[{"__symbolic":"call","expression":{"__symbolic":"reference","module":"@angular/core","name":"HostBinding","line":300,"character":5},"arguments":["attr.aria-valuemax"]}]}],"ariaValue":[{"__symbolic":"property","decorators":[{"__symbolic":"call","expression":{"__symbolic":"reference","module":"@angular/core","name":"HostBinding","line":304,"character":5},"arguments":["attr.aria-valuenow"]}]}],"__ctor__":[{"__symbolic":"constructor","parameters":[{"__symbolic":"reference","module":"@progress/kendo-angular-l10n","name":"LocalizationService","line":314,"character":37},{"__symbolic":"reference","module":"@angular/core","name":"Injector","line":315,"character":26},{"__symbolic":"reference","module":"@angular/core","name":"Renderer2","line":316,"character":26},{"__symbolic":"reference","module":"@angular/core","name":"NgZone","line":317,"character":24},{"__symbolic":"reference","module":"@angular/core","name":"ElementRef","line":318,"character":29}]}],"setDisabledState":[{"__symbolic":"method"}],"ngOnInit":[{"__symbolic":"method"}],"focus":[{"__symbolic":"method"}],"blur":[{"__symbolic":"method"}],"ngOnChanges":[{"__symbolic":"method"}],"ngAfterViewInit":[{"__symbolic":"method"}],"ngOnDestroy":[{"__symbolic":"method"}],"handleDragPress":[{"__symbolic":"method"}],"onHandleDrag":[{"__symbolic":"method"}],"onHandleRelease":[{"__symbolic":"method"}],"writeValue":[{"__symbolic":"method"}],"registerOnChange":[{"__symbolic":"method"}],"registerOnTouched":[{"__symbolic":"method"}],"changeValue":[{"__symbolic":"method"}],"sizeComponent":[{"__symbolic":"method"}],"isEmpty":[{"__symbolic":"method"}],"setValueChangeInterval":[{"__symbolic":"method"}],"handleAnimation":[{"__symbolic":"method"}],"getProps":[{"__symbolic":"method"}]}},"LabelTemplateDirective":{"__symbolic":"class","decorators":[{"__symbolic":"call","expression":{"__symbolic":"reference","module":"@angular/core","name":"Directive","line":26,"character":1},"arguments":[{"selector":"[kendoSliderLabelTemplate]"}]}],"members":{"__ctor__":[{"__symbolic":"constructor","parameterDecorators":[[{"__symbolic":"call","expression":{"__symbolic":"reference","module":"@angular/core","name":"Optional","line":30,"character":17}}]],"parameters":[{"__symbolic":"reference","name":"TemplateRef","module":"@angular/core","arguments":[{"__symbolic":"reference","name":"any"}]}]}]}},"SwitchComponent":{"__symbolic":"class","decorators":[{"__symbolic":"call","expression":{"__symbolic":"reference","module":"@angular/core","name":"Component","line":29,"character":1},"arguments":[{"exportAs":"kendoSwitch","providers":[{"__symbolic":"reference","module":"@progress/kendo-angular-l10n","name":"LocalizationService","line":32,"character":8},{"provide":{"__symbolic":"reference","module":"@progress/kendo-angular-l10n","name":"L10N_PREFIX","line":33,"character":19},"useValue":"kendo.switch"},{"multi":true,"provide":{"__symbolic":"reference","module":"@angular/forms","name":"NG_VALUE_ACCESSOR","line":36,"character":21},"useExisting":{"__symbolic":"reference","name":"SwitchComponent"}},{"provide":{"__symbolic":"reference","module":"@progress/kendo-angular-common","name":"KendoInput","line":40,"character":21},"useExisting":{"__symbolic":"reference","name":"SwitchComponent"}}],"selector":"kendo-switch","template":"\n        <ng-container kendoSwitchLocalizedMessages\n            i18n-on=\"kendo.switch.on|The **On** label of the Switch.\"\n            on=\"ON\"\n            i18n-off=\"kendo.switch.off|The **Off** label of the Switch.\"\n            off=\"OFF\"\n        >\n\n        <span\n            #wrapper\n            class=\"k-switch-container\"\n            [id]=\"focusableId\"\n            [attr.tabindex]=\"(disabled ? undefined : tabIndex)\"\n            [kendoEventsOutsideAngular]=\"{ click: clickHandler, keydown: keyDownHandler, focus: handleFocus, blur: handleBlur }\"\n        >\n            <span class=\"k-switch-label-on\">{{onLabelMessage}}</span>\n            <span class=\"k-switch-label-off\">{{offLabelMessage}}</span>\n            <span class=\"k-switch-handle\"></span>\n        </span>\n  "}]}],"members":{"focusableId":[{"__symbolic":"property","decorators":[{"__symbolic":"call","expression":{"__symbolic":"reference","module":"@angular/core","name":"Input","line":70,"character":5}}]}],"onLabel":[{"__symbolic":"property","decorators":[{"__symbolic":"call","expression":{"__symbolic":"reference","module":"@angular/core","name":"Input","line":75,"character":5}}]}],"offLabel":[{"__symbolic":"property","decorators":[{"__symbolic":"call","expression":{"__symbolic":"reference","module":"@angular/core","name":"Input","line":80,"character":5}}]}],"checked":[{"__symbolic":"property","decorators":[{"__symbolic":"call","expression":{"__symbolic":"reference","module":"@angular/core","name":"Input","line":85,"character":5}}]}],"disabled":[{"__symbolic":"property","decorators":[{"__symbolic":"call","expression":{"__symbolic":"reference","module":"@angular/core","name":"Input","line":90,"character":5}}]}],"readonly":[{"__symbolic":"property","decorators":[{"__symbolic":"call","expression":{"__symbolic":"reference","module":"@angular/core","name":"Input","line":95,"character":5}}]}],"tabindex":[{"__symbolic":"property","decorators":[{"__symbolic":"call","expression":{"__symbolic":"reference","module":"@angular/core","name":"Input","line":100,"character":5}}]}],"tabIndex":[{"__symbolic":"property","decorators":[{"__symbolic":"call","expression":{"__symbolic":"reference","module":"@angular/core","name":"Input","line":105,"character":5}}]}],"onFocus":[{"__symbolic":"property","decorators":[{"__symbolic":"call","expression":{"__symbolic":"reference","module":"@angular/core","name":"Output","line":116,"character":5},"arguments":["focus"]}]}],"onBlur":[{"__symbolic":"property","decorators":[{"__symbolic":"call","expression":{"__symbolic":"reference","module":"@angular/core","name":"Output","line":121,"character":5},"arguments":["blur"]}]}],"valueChange":[{"__symbolic":"property","decorators":[{"__symbolic":"call","expression":{"__symbolic":"reference","module":"@angular/core","name":"Output","line":126,"character":5}}]}],"wrapper":[{"__symbolic":"property","decorators":[{"__symbolic":"call","expression":{"__symbolic":"reference","module":"@angular/core","name":"ViewChild","line":128,"character":5},"arguments":["wrapper"]}]}],"direction":[{"__symbolic":"property","decorators":[{"__symbolic":"call","expression":{"__symbolic":"reference","module":"@angular/core","name":"HostBinding","line":130,"character":5},"arguments":["attr.dir"]}]}],"ieClass":[{"__symbolic":"property","decorators":[{"__symbolic":"call","expression":{"__symbolic":"reference","module":"@angular/core","name":"HostBinding","line":132,"character":5},"arguments":["class.k-ie"]}]}],"ariaDisabled":[{"__symbolic":"property","decorators":[{"__symbolic":"call","expression":{"__symbolic":"reference","module":"@angular/core","name":"HostBinding","line":137,"character":5},"arguments":["attr.aria-disabled"]}]}],"ariaReadonly":[{"__symbolic":"property","decorators":[{"__symbolic":"call","expression":{"__symbolic":"reference","module":"@angular/core","name":"HostBinding","line":142,"character":5},"arguments":["attr.aria-readonly"]}]}],"ariaChecked":[{"__symbolic":"property","decorators":[{"__symbolic":"call","expression":{"__symbolic":"reference","module":"@angular/core","name":"HostBinding","line":147,"character":5},"arguments":["attr.aria-checked"]}]}],"hostClasses":[{"__symbolic":"property","decorators":[{"__symbolic":"call","expression":{"__symbolic":"reference","module":"@angular/core","name":"HostBinding","line":152,"character":5},"arguments":["class.k-widget"]},{"__symbolic":"call","expression":{"__symbolic":"reference","module":"@angular/core","name":"HostBinding","line":153,"character":5},"arguments":["class.k-switch"]}]}],"switchOnClass":[{"__symbolic":"property","decorators":[{"__symbolic":"call","expression":{"__symbolic":"reference","module":"@angular/core","name":"HostBinding","line":158,"character":5},"arguments":["class.k-switch-on"]}]}],"switchOffClass":[{"__symbolic":"property","decorators":[{"__symbolic":"call","expression":{"__symbolic":"reference","module":"@angular/core","name":"HostBinding","line":163,"character":5},"arguments":["class.k-switch-off"]}]}],"disabledClass":[{"__symbolic":"property","decorators":[{"__symbolic":"call","expression":{"__symbolic":"reference","module":"@angular/core","name":"HostBinding","line":168,"character":5},"arguments":["class.k-state-disabled"]}]}],"__ctor__":[{"__symbolic":"constructor","parameters":[{"__symbolic":"reference","module":"@angular/core","name":"Renderer2","line":178,"character":26},{"__symbolic":"reference","module":"@angular/core","name":"ElementRef","line":179,"character":29},{"__symbolic":"reference","module":"@progress/kendo-angular-l10n","name":"LocalizationService","line":180,"character":37},{"__symbolic":"reference","module":"@angular/core","name":"Injector","line":181,"character":26},{"__symbolic":"reference","module":"@angular/core","name":"ChangeDetectorRef","line":182,"character":32},{"__symbolic":"reference","module":"@angular/core","name":"NgZone","line":183,"character":24}]}],"ngOnInit":[{"__symbolic":"method"}],"ngOnDestroy":[{"__symbolic":"method"}],"focus":[{"__symbolic":"method"}],"blur":[{"__symbolic":"method"}],"setDisabledState":[{"__symbolic":"method"}],"writeValue":[{"__symbolic":"method"}],"registerOnChange":[{"__symbolic":"method"}],"registerOnTouched":[{"__symbolic":"method"}],"keyDownHandler":[{"__symbolic":"method"}],"clickHandler":[{"__symbolic":"method"}],"isEmpty":[{"__symbolic":"method"}],"changeValue":[{"__symbolic":"method"}]}},"TextBoxContainerComponent":{"__symbolic":"class","decorators":[{"__symbolic":"call","expression":{"__symbolic":"reference","module":"@angular/core","name":"Component","line":55,"character":1},"arguments":[{"selector":"kendo-textbox-container","template":"\n        <ng-content></ng-content>\n        <label *ngIf=\"floatingLabel\" [for]=\"id\" class=\"k-label\">{{ floatingLabel }}</label>\n    "}]}],"members":{"hostClasses":[{"__symbolic":"property","decorators":[{"__symbolic":"call","expression":{"__symbolic":"reference","module":"@angular/core","name":"HostBinding","line":63,"character":5},"arguments":["class.k-textbox-container"]}]}],"textareaElementClass":[{"__symbolic":"property","decorators":[{"__symbolic":"call","expression":{"__symbolic":"reference","module":"@angular/core","name":"HostBinding","line":68,"character":5},"arguments":["class.k-textarea-wrapper"]}]}],"focusedClass":[{"__symbolic":"property","decorators":[{"__symbolic":"call","expression":{"__symbolic":"reference","module":"@angular/core","name":"HostBinding","line":73,"character":5},"arguments":["class.k-state-focused"]}]}],"emptyClass":[{"__symbolic":"property","decorators":[{"__symbolic":"call","expression":{"__symbolic":"reference","module":"@angular/core","name":"HostBinding","line":78,"character":5},"arguments":["class.k-state-empty"]}]}],"invalidClass":[{"__symbolic":"property","decorators":[{"__symbolic":"call","expression":{"__symbolic":"reference","module":"@angular/core","name":"HostBinding","line":83,"character":5},"arguments":["class.k-state-invalid"]}]}],"direction":[{"__symbolic":"property","decorators":[{"__symbolic":"call","expression":{"__symbolic":"reference","module":"@angular/core","name":"HostBinding","line":91,"character":5},"arguments":["attr.dir"]}]}],"id":[{"__symbolic":"property","decorators":[{"__symbolic":"call","expression":{"__symbolic":"reference","module":"@angular/core","name":"Input","line":96,"character":5}}]}],"floatingLabel":[{"__symbolic":"property","decorators":[{"__symbolic":"call","expression":{"__symbolic":"reference","module":"@angular/core","name":"Input","line":102,"character":5}}]}],"kendoInput":[{"__symbolic":"property","decorators":[{"__symbolic":"call","expression":{"__symbolic":"reference","module":"@angular/core","name":"ContentChild","line":105,"character":5},"arguments":[{"__symbolic":"reference","module":"@progress/kendo-angular-common","name":"KendoInput","line":105,"character":18}]}]}],"textarea":[{"__symbolic":"property","decorators":[{"__symbolic":"call","expression":{"__symbolic":"reference","module":"@angular/core","name":"ContentChild","line":108,"character":5},"arguments":[{"__symbolic":"reference","name":"TextAreaDirective"}]}]}],"formControl":[{"__symbolic":"property","decorators":[{"__symbolic":"call","expression":{"__symbolic":"reference","module":"@angular/core","name":"ContentChild","line":111,"character":5},"arguments":[{"__symbolic":"reference","module":"@angular/forms","name":"NgControl","line":111,"character":18}]}]}],"__ctor__":[{"__symbolic":"constructor","parameterDecorators":[null,null,null,[{"__symbolic":"call","expression":{"__symbolic":"reference","module":"@angular/core","name":"Optional","line":135,"character":9}},{"__symbolic":"call","expression":{"__symbolic":"reference","module":"@angular/core","name":"Inject","line":135,"character":21},"arguments":[{"__symbolic":"reference","module":"@progress/kendo-angular-l10n","name":"RTL","line":135,"character":28}]}]],"parameters":[{"__symbolic":"reference","module":"@angular/core","name":"ElementRef","line":132,"character":28},{"__symbolic":"reference","module":"@angular/core","name":"Renderer2","line":133,"character":26},{"__symbolic":"reference","module":"@angular/core","name":"ChangeDetectorRef","line":134,"character":35},{"__symbolic":"reference","name":"boolean"}]}],"ngAfterContentInit":[{"__symbolic":"method"}],"ngOnDestroy":[{"__symbolic":"method"}],"subscribe":[{"__symbolic":"method"}],"updateState":[{"__symbolic":"method"}]}},"TextBoxDirective":{"__symbolic":"class","decorators":[{"__symbolic":"call","expression":{"__symbolic":"reference","module":"@angular/core","name":"Directive","line":25,"character":1},"arguments":[{"selector":"input[kendoTextBox]","providers":[{"provide":{"__symbolic":"reference","module":"@progress/kendo-angular-common","name":"KendoInput","line":28,"character":17},"useExisting":{"__symbolic":"reference","name":"TextBoxDirective"}}]}]}],"members":{"hostClass":[{"__symbolic":"property","decorators":[{"__symbolic":"call","expression":{"__symbolic":"reference","module":"@angular/core","name":"HostBinding","line":34,"character":5},"arguments":["class.k-textbox"]}]}],"value":[{"__symbolic":"property","decorators":[{"__symbolic":"call","expression":{"__symbolic":"reference","module":"@angular/core","name":"Input","line":60,"character":5}}]}],"__ctor__":[{"__symbolic":"constructor","parameters":[{"__symbolic":"reference","module":"@angular/core","name":"Renderer2","line":84,"character":26},{"__symbolic":"reference","module":"@angular/core","name":"ElementRef","line":85,"character":30},{"__symbolic":"reference","module":"@angular/core","name":"NgZone","line":86,"character":24}]}],"ngAfterViewInit":[{"__symbolic":"method"}],"ngOnDestroy":[{"__symbolic":"method"}]}},"TextAreaDirective":{"__symbolic":"class","decorators":[{"__symbolic":"call","expression":{"__symbolic":"reference","module":"@angular/core","name":"Directive","line":36,"character":1},"arguments":[{"providers":[{"provide":{"__symbolic":"reference","module":"@angular/forms","name":"NG_VALUE_ACCESSOR","line":38,"character":17},"useExisting":{"__symbolic":"reference","name":"TextAreaDirective"},"multi":true},{"provide":{"__symbolic":"reference","module":"@progress/kendo-angular-common","name":"KendoInput","line":42,"character":17},"useExisting":{"__symbolic":"reference","name":"TextAreaDirective"}}],"selector":"textarea[kendoTextArea]"}]}],"members":{"elementClass":[{"__symbolic":"property","decorators":[{"__symbolic":"call","expression":{"__symbolic":"reference","module":"@angular/core","name":"HostBinding","line":48,"character":5},"arguments":["class.k-textarea"]}]}],"direction":[{"__symbolic":"property","decorators":[{"__symbolic":"call","expression":{"__symbolic":"reference","module":"@angular/core","name":"HostBinding","line":53,"character":5},"arguments":["attr.dir"]}]}],"valueChange":[{"__symbolic":"property","decorators":[{"__symbolic":"call","expression":{"__symbolic":"reference","module":"@angular/core","name":"Output","line":59,"character":5}}]}],"autoSize":[{"__symbolic":"property","decorators":[{"__symbolic":"call","expression":{"__symbolic":"reference","module":"@angular/core","name":"Input","line":68,"character":5}}]}],"value":[{"__symbolic":"property","decorators":[{"__symbolic":"call","expression":{"__symbolic":"reference","module":"@angular/core","name":"Input","line":74,"character":5}}]}],"__ctor__":[{"__symbolic":"constructor","parameterDecorators":[null,null,null,null,null,[{"__symbolic":"call","expression":{"__symbolic":"reference","module":"@angular/core","name":"Optional","line":112,"character":9}},{"__symbolic":"call","expression":{"__symbolic":"reference","module":"@angular/core","name":"Inject","line":112,"character":21},"arguments":[{"__symbolic":"reference","module":"@progress/kendo-angular-l10n","name":"RTL","line":112,"character":28}]}]],"parameters":[{"__symbolic":"reference","module":"@angular/core","name":"Renderer2","line":107,"character":26},{"__symbolic":"reference","module":"@angular/core","name":"ElementRef","line":108,"character":25},{"__symbolic":"reference","module":"@angular/core","name":"NgZone","line":109,"character":22},{"__symbolic":"reference","module":"@angular/core","name":"ChangeDetectorRef","line":110,"character":32},{"__symbolic":"reference","module":"@angular/core","name":"Injector","line":111,"character":26},{"__symbolic":"reference","name":"boolean"}]}],"writeValue":[{"__symbolic":"method"}],"registerOnChange":[{"__symbolic":"method"}],"registerOnTouched":[{"__symbolic":"method"}],"setDisabledState":[{"__symbolic":"method"}],"ngOnInit":[{"__symbolic":"method"}],"ngOnChanges":[{"__symbolic":"method"}],"ngOnDestroy":[{"__symbolic":"method"}],"setElementProperty":[{"__symbolic":"method"}],"resize":[{"__symbolic":"method"}],"handleInput":[{"__symbolic":"method"}],"handleFocus":[{"__symbolic":"method"}],"handleBlur":[{"__symbolic":"method"}]}},"NumericTextBoxComponent":{"__symbolic":"class","decorators":[{"__symbolic":"call","expression":{"__symbolic":"reference","module":"@angular/core","name":"Component","line":46,"character":1},"arguments":[{"exportAs":"kendoNumericTextBox","providers":[{"__symbolic":"reference","module":"@progress/kendo-angular-l10n","name":"LocalizationService","line":49,"character":8},{"provide":{"__symbolic":"reference","module":"@progress/kendo-angular-l10n","name":"L10N_PREFIX","line":50,"character":19},"useValue":"kendo.numerictextbox"},{"provide":{"__symbolic":"reference","module":"@angular/forms","name":"NG_VALUE_ACCESSOR","line":51,"character":19},"useExisting":{"__symbolic":"reference","name":"NumericTextBoxComponent"},"multi":true},{"provide":{"__symbolic":"reference","module":"@angular/forms","name":"NG_VALIDATORS","line":52,"character":19},"useExisting":{"__symbolic":"reference","name":"NumericTextBoxComponent"},"multi":true},{"provide":{"__symbolic":"reference","module":"@progress/kendo-angular-common","name":"KendoInput","line":53,"character":19},"useExisting":{"__symbolic":"reference","name":"NumericTextBoxComponent"}}],"selector":"kendo-numerictextbox","template":"\n        <ng-container kendoNumericTextBoxLocalizedMessages\n            i18n-increment=\"kendo.numerictextbox.increment|The title for the **Increment** button in the NumericTextBox\"\n            increment=\"Increase value\"\n            i18n-decrement=\"kendo.numerictextbox.decrement|The title for the **Decrement** button in the NumericTextBox\"\n            decrement=\"Decrease value\"\n        >\n        </ng-container>\n        <span\n            class=\"k-numeric-wrap\"\n            [class.k-state-disabled]=\"disabled\"\n            [kendoEventsOutsideAngular]=\"{ mousewheel: handleWheel, DOMMouseScroll: handleWheel }\"\n            #numericWrap>\n            <input\n            role=\"spinbutton\"\n            class=\"k-input k-formatted-value\"\n            autocomplete=\"off\"\n            autocorrect=\"off\"\n            [id]=\"focusableId\"\n            [attr.aria-valuemin]=\"min\"\n            [attr.aria-valuemax]=\"max\"\n            [attr.aria-valuenow]=\"value\"\n            [attr.title]=\"title\"\n            [attr.placeholder]=\"placeholder\"\n            [tabindex]=\"tabIndex\"\n            [disabled]=\"disabled\"\n            [readonly]=\"readonly\"\n            [kendoEventsOutsideAngular]=\"{\n                mousedown: handleMouseDown,\n                dragenter: handleDragEnter,\n                keydown: handleKeyDown,\n                input: handleInput,\n                focus: handleFocus,\n                blur: handleBlur,\n                paste: handlePaste\n            }\"\n            #numericInput />\n            <span class=\"k-select\" *ngIf=\"spinners\" [kendoEventsOutsideAngular]=\"{ mouseup: releaseArrow, mouseleave: releaseArrow }\">\n                <span\n                    [kendoEventsOutsideAngular]=\"{ mousedown: increasePress }\"\n                    [attr.aria-label]=\"incrementTitle\"\n                    [title]=\"incrementTitle\"\n                    [class.k-state-active]=\"arrowDirection === ArrowDirection.Up\"\n                    class=\"k-link k-link-increase\"\n                >\n                    <span class=\"k-icon k-i-arrow-n\"></span>\n                </span>\n                <span\n                    [kendoEventsOutsideAngular]=\"{ mousedown: decreasePress }\"\n                    [attr.aria-label]=\"decrementTitle\"\n                    [title]=\"decrementTitle\"\n                    [class.k-state-active]=\"arrowDirection === ArrowDirection.Down\"\n                    class=\"k-link k-link-decrease\"\n                >\n                    <span class=\"k-icon k-i-arrow-s\"></span>\n                </span>\n            </span>\n        </span>\n      "}]}],"members":{"focusableId":[{"__symbolic":"property","decorators":[{"__symbolic":"call","expression":{"__symbolic":"reference","module":"@angular/core","name":"Input","line":121,"character":5}}]}],"disabled":[{"__symbolic":"property","decorators":[{"__symbolic":"call","expression":{"__symbolic":"reference","module":"@angular/core","name":"Input","line":126,"character":5}}]}],"readonly":[{"__symbolic":"property","decorators":[{"__symbolic":"call","expression":{"__symbolic":"reference","module":"@angular/core","name":"Input","line":131,"character":5}}]}],"title":[{"__symbolic":"property","decorators":[{"__symbolic":"call","expression":{"__symbolic":"reference","module":"@angular/core","name":"Input","line":136,"character":5}}]}],"autoCorrect":[{"__symbolic":"property","decorators":[{"__symbolic":"call","expression":{"__symbolic":"reference","module":"@angular/core","name":"Input","line":142,"character":5}}]}],"format":[{"__symbolic":"property","decorators":[{"__symbolic":"call","expression":{"__symbolic":"reference","module":"@angular/core","name":"Input","line":154,"character":5}}]}],"max":[{"__symbolic":"property","decorators":[{"__symbolic":"call","expression":{"__symbolic":"reference","module":"@angular/core","name":"Input","line":162,"character":5}}]}],"min":[{"__symbolic":"property","decorators":[{"__symbolic":"call","expression":{"__symbolic":"reference","module":"@angular/core","name":"Input","line":168,"character":5}}]}],"decimals":[{"__symbolic":"property","decorators":[{"__symbolic":"call","expression":{"__symbolic":"reference","module":"@angular/core","name":"Input","line":174,"character":5}}]}],"placeholder":[{"__symbolic":"property","decorators":[{"__symbolic":"call","expression":{"__symbolic":"reference","module":"@angular/core","name":"Input","line":179,"character":5}}]}],"step":[{"__symbolic":"property","decorators":[{"__symbolic":"call","expression":{"__symbolic":"reference","module":"@angular/core","name":"Input","line":186,"character":5}}]}],"spinners":[{"__symbolic":"property","decorators":[{"__symbolic":"call","expression":{"__symbolic":"reference","module":"@angular/core","name":"Input","line":192,"character":5}}]}],"rangeValidation":[{"__symbolic":"property","decorators":[{"__symbolic":"call","expression":{"__symbolic":"reference","module":"@angular/core","name":"Input","line":200,"character":5}}]}],"tabindex":[{"__symbolic":"property","decorators":[{"__symbolic":"call","expression":{"__symbolic":"reference","module":"@angular/core","name":"Input","line":205,"character":5}}]}],"tabIndex":[{"__symbolic":"property","decorators":[{"__symbolic":"call","expression":{"__symbolic":"reference","module":"@angular/core","name":"Input","line":210,"character":5}}]}],"selectOnFocus":[{"__symbolic":"property","decorators":[{"__symbolic":"call","expression":{"__symbolic":"reference","module":"@angular/core","name":"Input","line":221,"character":5}}]}],"value":[{"__symbolic":"property","decorators":[{"__symbolic":"call","expression":{"__symbolic":"reference","module":"@angular/core","name":"Input","line":227,"character":5}}]}],"valueChange":[{"__symbolic":"property","decorators":[{"__symbolic":"call","expression":{"__symbolic":"reference","module":"@angular/core","name":"Output","line":232,"character":5}}]}],"onFocus":[{"__symbolic":"property","decorators":[{"__symbolic":"call","expression":{"__symbolic":"reference","module":"@angular/core","name":"Output","line":237,"character":5},"arguments":["focus"]}]}],"onBlur":[{"__symbolic":"property","decorators":[{"__symbolic":"call","expression":{"__symbolic":"reference","module":"@angular/core","name":"Output","line":242,"character":5},"arguments":["blur"]}]}],"numericInput":[{"__symbolic":"property","decorators":[{"__symbolic":"call","expression":{"__symbolic":"reference","module":"@angular/core","name":"ViewChild","line":247,"character":5},"arguments":["numericInput"]}]}],"numericWrap":[{"__symbolic":"property","decorators":[{"__symbolic":"call","expression":{"__symbolic":"reference","module":"@angular/core","name":"ViewChild","line":248,"character":5},"arguments":["numericWrap"]}]}],"direction":[{"__symbolic":"property","decorators":[{"__symbolic":"call","expression":{"__symbolic":"reference","module":"@angular/core","name":"HostBinding","line":250,"character":5},"arguments":["attr.dir"]}]}],"widgetClasses":[{"__symbolic":"property","decorators":[{"__symbolic":"call","expression":{"__symbolic":"reference","module":"@angular/core","name":"HostBinding","line":261,"character":5},"arguments":["class.k-widget"]},{"__symbolic":"call","expression":{"__symbolic":"reference","module":"@angular/core","name":"HostBinding","line":262,"character":5},"arguments":["class.k-numerictextbox"]}]}],"__ctor__":[{"__symbolic":"constructor","parameters":[{"__symbolic":"reference","module":"@progress/kendo-angular-intl","name":"IntlService","line":290,"character":22},{"__symbolic":"reference","module":"@angular/core","name":"Renderer2","line":291,"character":26},{"__symbolic":"reference","module":"@progress/kendo-angular-l10n","name":"LocalizationService","line":292,"character":37},{"__symbolic":"reference","module":"@angular/core","name":"Injector","line":293,"character":26},{"__symbolic":"reference","module":"@angular/core","name":"NgZone","line":294,"character":24},{"__symbolic":"reference","module":"@angular/core","name":"ChangeDetectorRef","line":295,"character":32},{"__symbolic":"reference","module":"@angular/core","name":"ElementRef","line":296,"character":29}]}],"ngOnInit":[{"__symbolic":"method"}],"ngOnChanges":[{"__symbolic":"method"}],"ngOnDestroy":[{"__symbolic":"method"}],"validate":[{"__symbolic":"method"}],"registerOnValidatorChange":[{"__symbolic":"method"}],"writeValue":[{"__symbolic":"method"}],"registerOnChange":[{"__symbolic":"method"}],"registerOnTouched":[{"__symbolic":"method"}],"setDisabledState":[{"__symbolic":"method"}],"focus":[{"__symbolic":"method"}],"blur":[{"__symbolic":"method"}],"notifyValueChange":[{"__symbolic":"method"}],"arrowPress":[{"__symbolic":"method"}],"updateValue":[{"__symbolic":"method"}],"replaceNumpadDotValue":[{"__symbolic":"method"}],"isValid":[{"__symbolic":"method"}],"spin":[{"__symbolic":"method"}],"addStep":[{"__symbolic":"method"}],"setSelection":[{"__symbolic":"method"}],"limitValue":[{"__symbolic":"method"}],"limitInputValue":[{"__symbolic":"method"}],"tryPadValue":[{"__symbolic":"method"}],"isInRange":[{"__symbolic":"method"}],"restrictModelValue":[{"__symbolic":"method"}],"restrictDecimals":[{"__symbolic":"method"}],"formatInputValue":[{"__symbolic":"method"}],"formatValue":[{"__symbolic":"method"}],"setInputValue":[{"__symbolic":"method"}],"verifySettings":[{"__symbolic":"method"}],"verifyValue":[{"__symbolic":"method"}],"parseOptions":[{"__symbolic":"method"}],"intlChange":[{"__symbolic":"method"}],"hasTrailingZeros":[{"__symbolic":"method"}],"selectAll":[{"__symbolic":"method"}],"selectCaret":[{"__symbolic":"method"}],"numberOfLeadingZeroes":[{"__symbolic":"method"}],"adjustSignificantChars":[{"__symbolic":"method"}]}},"NumericTextBoxCustomMessagesComponent":{"__symbolic":"class","extends":{"__symbolic":"reference","name":"Messages"},"decorators":[{"__symbolic":"call","expression":{"__symbolic":"reference","module":"@angular/core","name":"Component","line":7,"character":1},"arguments":[{"providers":[{"provide":{"__symbolic":"reference","name":"Messages"},"useExisting":{"__symbolic":"reference","name":"NumericTextBoxCustomMessagesComponent"}}],"selector":"kendo-numerictextbox-messages","template":""}]}],"members":{"__ctor__":[{"__symbolic":"constructor","parameters":[{"__symbolic":"reference","module":"@progress/kendo-angular-l10n","name":"LocalizationService","line":18,"character":35}]}]}},"MaskedTextBoxComponent":{"__symbolic":"class","decorators":[{"__symbolic":"call","expression":{"__symbolic":"reference","module":"@angular/core","name":"Component","line":62,"character":1},"arguments":[{"exportAs":"kendoMaskedTextBox","providers":[{"__symbolic":"reference","name":"MaskingService"},{"multi":true,"provide":{"__symbolic":"reference","module":"@angular/forms","name":"NG_VALUE_ACCESSOR","line":68,"character":21},"useExisting":{"__symbolic":"reference","name":"MaskedTextBoxComponent"}},{"multi":true,"provide":{"__symbolic":"reference","module":"@angular/forms","name":"NG_VALIDATORS","line":73,"character":21},"useExisting":{"__symbolic":"reference","name":"MaskedTextBoxComponent"}},{"provide":{"__symbolic":"reference","module":"@progress/kendo-angular-common","name":"KendoInput","line":77,"character":21},"useExisting":{"__symbolic":"reference","name":"MaskedTextBoxComponent"}}],"selector":"kendo-maskedtextbox","template":"\n        <input type=\"text\"\n            #input\n            autocomplete=\"off\"\n            autocorrect=\"off\"\n            autocapitalize=\"off\"\n            spellcheck=\"false\"\n            class=\"k-textbox\"\n            [id]=\"focusableId\"\n            [tabindex]=\"tabIndex\"\n            [attr.title]=\"title\"\n            [disabled]=\"disabled\"\n            [readonly]=\"readonly\"\n            [kendoEventsOutsideAngular]=\"{\n                focus: handleFocus,\n                blur: handleBlur,\n                click: handleClick,\n                dragstart: handleDragDrop,\n                drop: handleDragDrop\n            }\"\n        />\n    "}]}],"members":{"focusableId":[{"__symbolic":"property","decorators":[{"__symbolic":"call","expression":{"__symbolic":"reference","module":"@angular/core","name":"Input","line":110,"character":5}}]}],"disabled":[{"__symbolic":"property","decorators":[{"__symbolic":"call","expression":{"__symbolic":"reference","module":"@angular/core","name":"Input","line":115,"character":5}}]}],"readonly":[{"__symbolic":"property","decorators":[{"__symbolic":"call","expression":{"__symbolic":"reference","module":"@angular/core","name":"Input","line":120,"character":5}}]}],"title":[{"__symbolic":"property","decorators":[{"__symbolic":"call","expression":{"__symbolic":"reference","module":"@angular/core","name":"Input","line":125,"character":5}}]}],"direction":[{"__symbolic":"property","decorators":[{"__symbolic":"call","expression":{"__symbolic":"reference","module":"@angular/core","name":"HostBinding","line":127,"character":5},"arguments":["attr.dir"]}]}],"hostClasses":[{"__symbolic":"property","decorators":[{"__symbolic":"call","expression":{"__symbolic":"reference","module":"@angular/core","name":"HostBinding","line":129,"character":5},"arguments":["class.k-widget"]},{"__symbolic":"call","expression":{"__symbolic":"reference","module":"@angular/core","name":"HostBinding","line":130,"character":5},"arguments":["class.k-maskedtextbox"]}]}],"hostDisabledClass":[{"__symbolic":"property","decorators":[{"__symbolic":"call","expression":{"__symbolic":"reference","module":"@angular/core","name":"HostBinding","line":133,"character":5},"arguments":["class.k-state-disabled"]}]}],"mask":[{"__symbolic":"property","decorators":[{"__symbolic":"call","expression":{"__symbolic":"reference","module":"@angular/core","name":"Input","line":145,"character":5}}]}],"value":[{"__symbolic":"property","decorators":[{"__symbolic":"call","expression":{"__symbolic":"reference","module":"@angular/core","name":"Input","line":150,"character":5}}]}],"rules":[{"__symbolic":"property","decorators":[{"__symbolic":"call","expression":{"__symbolic":"reference","module":"@angular/core","name":"Input","line":159,"character":5}}]}],"prompt":[{"__symbolic":"property","decorators":[{"__symbolic":"call","expression":{"__symbolic":"reference","module":"@angular/core","name":"Input","line":167,"character":5}}]}],"promptPlaceholder":[{"__symbolic":"property","decorators":[{"__symbolic":"call","expression":{"__symbolic":"reference","module":"@angular/core","name":"Input","line":173,"character":5}}]}],"includeLiterals":[{"__symbolic":"property","decorators":[{"__symbolic":"call","expression":{"__symbolic":"reference","module":"@angular/core","name":"Input","line":179,"character":5}}]}],"maskOnFocus":[{"__symbolic":"property","decorators":[{"__symbolic":"call","expression":{"__symbolic":"reference","module":"@angular/core","name":"Input","line":184,"character":5}}]}],"maskValidation":[{"__symbolic":"property","decorators":[{"__symbolic":"call","expression":{"__symbolic":"reference","module":"@angular/core","name":"Input","line":191,"character":5}}]}],"tabindex":[{"__symbolic":"property","decorators":[{"__symbolic":"call","expression":{"__symbolic":"reference","module":"@angular/core","name":"Input","line":196,"character":5}}]}],"tabIndex":[{"__symbolic":"property","decorators":[{"__symbolic":"call","expression":{"__symbolic":"reference","module":"@angular/core","name":"Input","line":201,"character":5}}]}],"onFocus":[{"__symbolic":"property","decorators":[{"__symbolic":"call","expression":{"__symbolic":"reference","module":"@angular/core","name":"Output","line":229,"character":5},"arguments":["focus"]}]}],"onBlur":[{"__symbolic":"property","decorators":[{"__symbolic":"call","expression":{"__symbolic":"reference","module":"@angular/core","name":"Output","line":251,"character":5},"arguments":["blur"]}]}],"valueChange":[{"__symbolic":"property","decorators":[{"__symbolic":"call","expression":{"__symbolic":"reference","module":"@angular/core","name":"Output","line":256,"character":5}}]}],"input":[{"__symbolic":"property","decorators":[{"__symbolic":"call","expression":{"__symbolic":"reference","module":"@angular/core","name":"ViewChild","line":261,"character":5},"arguments":["input"]}]}],"__ctor__":[{"__symbolic":"constructor","parameterDecorators":[null,null,null,null,null,[{"__symbolic":"call","expression":{"__symbolic":"reference","module":"@angular/core","name":"Optional","line":288,"character":17}},{"__symbolic":"call","expression":{"__symbolic":"reference","module":"@angular/core","name":"Inject","line":288,"character":29},"arguments":[{"__symbolic":"reference","module":"@progress/kendo-angular-l10n","name":"RTL","line":288,"character":36}]}]],"parameters":[{"__symbolic":"reference","name":"MaskingService"},{"__symbolic":"reference","module":"@angular/core","name":"Renderer2","line":284,"character":34},{"__symbolic":"reference","module":"@angular/core","name":"ElementRef","line":285,"character":37},{"__symbolic":"reference","module":"@angular/core","name":"NgZone","line":286,"character":32},{"__symbolic":"reference","module":"@angular/core","name":"Injector","line":287,"character":34},{"__symbolic":"reference","name":"boolean"}]}],"ngOnInit":[{"__symbolic":"method"}],"isEmpty":[{"__symbolic":"method"}],"handleDragDrop":[{"__symbolic":"method"}],"focus":[{"__symbolic":"method"}],"blur":[{"__symbolic":"method"}],"pasteHandler":[{"__symbolic":"method","decorators":[{"__symbolic":"call","expression":{"__symbolic":"reference","module":"@angular/core","name":"HostListener","line":402,"character":5},"arguments":["paste",["$event"]]}]}],"inputHandler":[{"__symbolic":"method","decorators":[{"__symbolic":"call","expression":{"__symbolic":"reference","module":"@angular/core","name":"HostListener","line":416,"character":5},"arguments":["input",["$event"]]}]}],"ngOnChanges":[{"__symbolic":"method"}],"writeValue":[{"__symbolic":"method"}],"registerOnChange":[{"__symbolic":"method"}],"registerOnTouched":[{"__symbolic":"method"}],"setDisabledState":[{"__symbolic":"method"}],"validate":[{"__symbolic":"method"}],"updateValue":[{"__symbolic":"method"}],"updateInput":[{"__symbolic":"method"}],"extractChanges":[{"__symbolic":"method"}],"updateService":[{"__symbolic":"method"}],"setSelection":[{"__symbolic":"method"}],"setFocusSelection":[{"__symbolic":"method"}],"normalizeValue":[{"__symbolic":"method"}]}},"InputsModule":{"__symbolic":"class","decorators":[{"__symbolic":"call","expression":{"__symbolic":"reference","module":"@angular/core","name":"NgModule","line":41,"character":1},"arguments":[{"exports":[{"__symbolic":"reference","name":"TextBoxModule"},{"__symbolic":"reference","name":"SliderModule"},{"__symbolic":"reference","name":"SwitchModule"},{"__symbolic":"reference","name":"NumericTextBoxModule"},{"__symbolic":"reference","name":"MaskedTextBoxModule"},{"__symbolic":"reference","name":"ColorPickerModule"}],"imports":[{"__symbolic":"reference","module":"@angular/common","name":"CommonModule","line":43,"character":14}]}]}],"members":{}},"SliderTicksComponent":{"__symbolic":"class","decorators":[{"__symbolic":"call","expression":{"__symbolic":"reference","module":"@angular/core","name":"Component","line":35,"character":1},"arguments":[{"selector":"[kendoSliderTicks]","template":"\n    <li #tickElement *ngFor=\"let tick of ticks;\"\n        [ngClass]=\"tick.classes\"\n        title=\"{{ tickTitle(tick.value) }}\"\n        role=\"presentation\"\n     >\n         <ng-container [ngSwitch]=\"tick.large\">\n            <span class=\"k-label\" *ngSwitchCase=\"true\">\n                <ng-container [ngTemplateOutlet]=\"labelTemplate || defaultLabel\" [ngTemplateOutletContext]=\"tick\">\n                </ng-container>\n            </span>\n            <ng-container *ngSwitchCase=\"false\">&nbsp;</ng-container>\n         </ng-container>\n     </li>\n\n     <ng-template #defaultLabel let-value=\"value\">\n        {{ tickTitle(value) }}\n     </ng-template>\n  "}]}],"members":{"wrapperClasses":[{"__symbolic":"property","decorators":[{"__symbolic":"call","expression":{"__symbolic":"reference","module":"@angular/core","name":"HostBinding","line":58,"character":5},"arguments":["class"]}]}],"tickTitle":[{"__symbolic":"property","decorators":[{"__symbolic":"call","expression":{"__symbolic":"reference","module":"@angular/core","name":"Input","line":61,"character":5}}]}],"vertical":[{"__symbolic":"property","decorators":[{"__symbolic":"call","expression":{"__symbolic":"reference","module":"@angular/core","name":"Input","line":62,"character":5}}]}],"step":[{"__symbolic":"property","decorators":[{"__symbolic":"call","expression":{"__symbolic":"reference","module":"@angular/core","name":"Input","line":63,"character":5}}]}],"largeStep":[{"__symbolic":"property","decorators":[{"__symbolic":"call","expression":{"__symbolic":"reference","module":"@angular/core","name":"Input","line":64,"character":5}}]}],"min":[{"__symbolic":"property","decorators":[{"__symbolic":"call","expression":{"__symbolic":"reference","module":"@angular/core","name":"Input","line":65,"character":5}}]}],"max":[{"__symbolic":"property","decorators":[{"__symbolic":"call","expression":{"__symbolic":"reference","module":"@angular/core","name":"Input","line":66,"character":5}}]}],"labelTemplate":[{"__symbolic":"property","decorators":[{"__symbolic":"call","expression":{"__symbolic":"reference","module":"@angular/core","name":"Input","line":67,"character":5}}]}],"tickElements":[{"__symbolic":"property","decorators":[{"__symbolic":"call","expression":{"__symbolic":"reference","module":"@angular/core","name":"ViewChildren","line":69,"character":5},"arguments":["tickElement"]}]}],"__ctor__":[{"__symbolic":"constructor","parameterDecorators":[[{"__symbolic":"call","expression":{"__symbolic":"reference","module":"@angular/core","name":"Optional","line":72,"character":17}},{"__symbolic":"call","expression":{"__symbolic":"reference","module":"@angular/core","name":"Inject","line":72,"character":29},"arguments":[{"__symbolic":"reference","module":"@progress/kendo-angular-l10n","name":"RTL","line":72,"character":36}]}]],"parameters":[{"__symbolic":"reference","name":"boolean"}]}],"ngOnChanges":[{"__symbolic":"method"}],"createTicks":[{"__symbolic":"method"}],"endTickClasses":[{"__symbolic":"method"}]}},"SliderModule":{"__symbolic":"class","decorators":[{"__symbolic":"call","expression":{"__symbolic":"reference","module":"@angular/core","name":"NgModule","line":57,"character":1},"arguments":[{"declarations":[{"__symbolic":"reference","name":"SliderComponent"},{"__symbolic":"reference","name":"SliderTicksComponent"},{"__symbolic":"reference","name":"SliderCustomMessagesComponent"},{"__symbolic":"reference","name":"LocalizedMessagesDirective$1"},{"__symbolic":"reference","name":"LabelTemplateDirective"}],"exports":[{"__symbolic":"reference","name":"SliderComponent"},{"__symbolic":"reference","name":"SliderCustomMessagesComponent"},{"__symbolic":"reference","name":"LocalizedMessagesDirective$1"},{"__symbolic":"reference","name":"LabelTemplateDirective"}],"imports":[{"__symbolic":"reference","module":"@angular/common","name":"CommonModule","line":60,"character":14},{"__symbolic":"reference","module":"@progress/kendo-angular-common","name":"DraggableModule","line":60,"character":28},{"__symbolic":"reference","module":"@progress/kendo-angular-common","name":"EventsModule","line":60,"character":45},{"__symbolic":"reference","module":"@progress/kendo-angular-common","name":"ResizeSensorModule","line":60,"character":59}]}]}],"members":{}},"SwitchModule":{"__symbolic":"class","decorators":[{"__symbolic":"call","expression":{"__symbolic":"reference","module":"@angular/core","name":"NgModule","line":51,"character":1},"arguments":[{"declarations":[{"__symbolic":"reference","name":"SwitchComponent"},{"__symbolic":"reference","name":"SwitchCustomMessagesComponent"},{"__symbolic":"reference","name":"LocalizedMessagesDirective$2"}],"exports":[{"__symbolic":"reference","name":"SwitchComponent"},{"__symbolic":"reference","name":"SwitchCustomMessagesComponent"},{"__symbolic":"reference","name":"LocalizedMessagesDirective$2"}],"imports":[{"__symbolic":"reference","module":"@angular/common","name":"CommonModule","line":54,"character":14},{"__symbolic":"reference","module":"@progress/kendo-angular-common","name":"EventsModule","line":54,"character":28},{"__symbolic":"reference","module":"@progress/kendo-angular-common","name":"ResizeSensorModule","line":54,"character":42}]}]}],"members":{}},"NumericTextBoxModule":{"__symbolic":"class","decorators":[{"__symbolic":"call","expression":{"__symbolic":"reference","module":"@angular/core","name":"NgModule","line":48,"character":1},"arguments":[{"declarations":[[{"__symbolic":"reference","name":"LocalizedMessagesDirective"},{"__symbolic":"reference","name":"NumericTextBoxComponent"},{"__symbolic":"reference","name":"NumericTextBoxCustomMessagesComponent"}]],"exports":[[{"__symbolic":"reference","name":"NumericTextBoxComponent"},{"__symbolic":"reference","name":"NumericTextBoxCustomMessagesComponent"}]],"imports":[{"__symbolic":"reference","module":"@angular/common","name":"CommonModule","line":51,"character":14},{"__symbolic":"reference","module":"@progress/kendo-angular-common","name":"EventsModule","line":51,"character":28}]}]}],"members":{}},"MaskedTextBoxModule":{"__symbolic":"class","decorators":[{"__symbolic":"call","expression":{"__symbolic":"reference","module":"@angular/core","name":"NgModule","line":36,"character":1},"arguments":[{"declarations":[{"__symbolic":"reference","name":"MaskedTextBoxComponent"}],"exports":[{"__symbolic":"reference","name":"MaskedTextBoxComponent"}],"imports":[{"__symbolic":"reference","module":"@angular/common","name":"CommonModule","line":39,"character":14},{"__symbolic":"reference","module":"@progress/kendo-angular-common","name":"EventsModule","line":39,"character":28}]}]}],"members":{}},"TextBoxModule":{"__symbolic":"class","decorators":[{"__symbolic":"call","expression":{"__symbolic":"reference","module":"@angular/core","name":"NgModule","line":37,"character":1},"arguments":[{"declarations":[{"__symbolic":"reference","name":"TextBoxDirective"},{"__symbolic":"reference","name":"TextAreaDirective"},{"__symbolic":"reference","name":"TextBoxContainerComponent"}],"exports":[{"__symbolic":"reference","name":"TextBoxDirective"},{"__symbolic":"reference","name":"TextAreaDirective"},{"__symbolic":"reference","name":"TextBoxContainerComponent"}],"imports":[{"__symbolic":"reference","module":"@angular/common","name":"CommonModule","line":40,"character":14}]}]}],"members":{}},"ColorPickerComponent":{"__symbolic":"class","decorators":[{"__symbolic":"call","expression":{"__symbolic":"reference","module":"@angular/core","name":"Component","line":41,"character":1},"arguments":[{"selector":"kendo-colorpicker","providers":[{"multi":true,"provide":{"__symbolic":"reference","module":"@angular/forms","name":"NG_VALUE_ACCESSOR","line":45,"character":17},"useExisting":{"__symbolic":"reference","name":"ColorPickerComponent"}},{"provide":{"__symbolic":"reference","module":"@progress/kendo-angular-common","name":"KendoInput","line":48,"character":17},"useExisting":{"__symbolic":"reference","name":"ColorPickerComponent"}},{"__symbolic":"reference","module":"@progress/kendo-angular-l10n","name":"LocalizationService","line":51,"character":4},{"provide":{"__symbolic":"reference","module":"@progress/kendo-angular-l10n","name":"L10N_PREFIX","line":53,"character":21},"useValue":"kendo.colorpicker"}],"template":"\n        <span\n            #wrapper\n            [ngClass]=\"{\n                'k-picker-wrap': true,\n                'k-state-default': !this.disabled,\n                'k-state-disabled': this.disabled,\n                'k-state-focused': this.isFocused\n            }\"\n            [attr.tabindex]=\"tabindex\"\n            (focus)=\"handleWrapperFocus()\"\n            (blur)=\"handleWrapperBlur()\"\n            (mousedown)=\"$event.preventDefault()\"\n            (keydown)=\"handleWrapperKeyDown($event)\"\n        >\n            <span *ngIf=\"!iconStyles\" class=\"k-selected-color\" [style.background-color]=\"value\" (click)=\"handleActiveColorClick()\">\n                <span class=\"k-icon k-i-line\" *ngIf=\"!value\"></span>\n            </span>\n            <span *ngIf=\"iconStyles\" class=\"k-tool-icon\" [ngClass]=\"iconStyles\" (click)=\"handleActiveColorClick()\">\n                <span class=\"k-selected-color\" [style.background-color]=\"value\"></span>\n            </span>\n            <span class=\"k-select\" (click)=\"handleWrapperClick()\">\n                <span class=\"k-icon k-i-arrow-s\"></span>\n            </span>\n        </span>\n        <ng-template #popupTemplate>\n            <kendo-colorgradient\n                *ngIf=\"view === 'gradient' || view === 'combo'\"\n                kendoFocusOnDomReady\n                [value]=\"value\"\n                [format]=\"format\"\n                [opacity]=\"gradientSettings.opacity\"\n                [clearButton]=\"gradientSettings.clearButton\"\n                (focusout)=\"handlePopupBlur($event)\"\n                (valueChange)=\"handleValueChange($event, false)\"\n                (keydown)=\"handlePopupKeyDown($event.keyCode)\"\n            >\n            </kendo-colorgradient>\n            <kendo-colorpalette\n                #palette\n                *ngIf=\"view === 'palette' || view === 'combo'\"\n                kendoFocusOnDomReady\n                [palette]=\"paletteSettings.palette\"\n                [columns]=\"paletteSettings.columns\"\n                [tileSize]=\"paletteSettings.tileSize\"\n                [format]=\"format\"\n                [value]=\"value\"\n                (blur)=\"handlePopupBlur($event)\"\n                (cellSelection)=\"handleValueChange($event, true)\"\n                (mousedown)=\"$event.preventDefault()\"\n                (keydown)=\"handlePopupKeyDown($event.keyCode)\"\n            >\n            </kendo-colorpalette>\n        </ng-template>\n        <ng-container #container></ng-container>\n    "}]}],"members":{"hostClasses":[{"__symbolic":"property","decorators":[{"__symbolic":"call","expression":{"__symbolic":"reference","module":"@angular/core","name":"HostBinding","line":118,"character":5},"arguments":["class.k-widget"]},{"__symbolic":"call","expression":{"__symbolic":"reference","module":"@angular/core","name":"HostBinding","line":119,"character":5},"arguments":["class.k-colorpicker"]}]}],"direction":[{"__symbolic":"property","decorators":[{"__symbolic":"call","expression":{"__symbolic":"reference","module":"@angular/core","name":"HostBinding","line":125,"character":5},"arguments":["attr.dir"]}]}],"view":[{"__symbolic":"property","decorators":[{"__symbolic":"call","expression":{"__symbolic":"reference","module":"@angular/core","name":"Input","line":130,"character":5}}]}],"readonly":[{"__symbolic":"property","decorators":[{"__symbolic":"call","expression":{"__symbolic":"reference","module":"@angular/core","name":"Input","line":135,"character":5}}]}],"disabled":[{"__symbolic":"property","decorators":[{"__symbolic":"call","expression":{"__symbolic":"reference","module":"@angular/core","name":"Input","line":140,"character":5}}]}],"format":[{"__symbolic":"property","decorators":[{"__symbolic":"call","expression":{"__symbolic":"reference","module":"@angular/core","name":"Input","line":154,"character":5}}]}],"value":[{"__symbolic":"property","decorators":[{"__symbolic":"call","expression":{"__symbolic":"reference","module":"@angular/core","name":"Input","line":158,"character":5}}]}],"popupSettings":[{"__symbolic":"property","decorators":[{"__symbolic":"call","expression":{"__symbolic":"reference","module":"@angular/core","name":"Input","line":168,"character":5}}]}],"paletteSettings":[{"__symbolic":"property","decorators":[{"__symbolic":"call","expression":{"__symbolic":"reference","module":"@angular/core","name":"Input","line":178,"character":5}}]}],"gradientSettings":[{"__symbolic":"property","decorators":[{"__symbolic":"call","expression":{"__symbolic":"reference","module":"@angular/core","name":"Input","line":188,"character":5}}]}],"icon":[{"__symbolic":"property","decorators":[{"__symbolic":"call","expression":{"__symbolic":"reference","module":"@angular/core","name":"Input","line":200,"character":5}}]}],"iconClass":[{"__symbolic":"property","decorators":[{"__symbolic":"call","expression":{"__symbolic":"reference","module":"@angular/core","name":"Input","line":208,"character":5}}]}],"tabindex":[{"__symbolic":"property","decorators":[{"__symbolic":"call","expression":{"__symbolic":"reference","module":"@angular/core","name":"Input","line":213,"character":5}}]}],"valueChange":[{"__symbolic":"property","decorators":[{"__symbolic":"call","expression":{"__symbolic":"reference","module":"@angular/core","name":"Output","line":226,"character":5}}]}],"open":[{"__symbolic":"property","decorators":[{"__symbolic":"call","expression":{"__symbolic":"reference","module":"@angular/core","name":"Output","line":232,"character":5}}]}],"close":[{"__symbolic":"property","decorators":[{"__symbolic":"call","expression":{"__symbolic":"reference","module":"@angular/core","name":"Output","line":238,"character":5}}]}],"onFocus":[{"__symbolic":"property","decorators":[{"__symbolic":"call","expression":{"__symbolic":"reference","module":"@angular/core","name":"Output","line":243,"character":5},"arguments":["focus"]}]}],"onBlur":[{"__symbolic":"property","decorators":[{"__symbolic":"call","expression":{"__symbolic":"reference","module":"@angular/core","name":"Output","line":248,"character":5},"arguments":["blur"]}]}],"activeColorClick":[{"__symbolic":"property","decorators":[{"__symbolic":"call","expression":{"__symbolic":"reference","module":"@angular/core","name":"Output","line":256,"character":5}}]}],"container":[{"__symbolic":"property","decorators":[{"__symbolic":"call","expression":{"__symbolic":"reference","module":"@angular/core","name":"ViewChild","line":288,"character":5},"arguments":["container",{"read":{"__symbolic":"reference","module":"@angular/core","name":"ViewContainerRef","line":288,"character":36}}]}]}],"wrapper":[{"__symbolic":"property","decorators":[{"__symbolic":"call","expression":{"__symbolic":"reference","module":"@angular/core","name":"ViewChild","line":290,"character":5},"arguments":["wrapper"]}]}],"popupTemplate":[{"__symbolic":"property","decorators":[{"__symbolic":"call","expression":{"__symbolic":"reference","module":"@angular/core","name":"ViewChild","line":291,"character":5},"arguments":["popupTemplate"]}]}],"palette":[{"__symbolic":"property","decorators":[{"__symbolic":"call","expression":{"__symbolic":"reference","module":"@angular/core","name":"ViewChild","line":292,"character":5},"arguments":["palette",{"read":{"__symbolic":"reference","module":"@angular/core","name":"ElementRef","line":292,"character":34}}]}]}],"__ctor__":[{"__symbolic":"constructor","parameters":[{"__symbolic":"reference","module":"@progress/kendo-angular-popup","name":"PopupService","line":303,"character":38},{"__symbolic":"reference","module":"@progress/kendo-angular-l10n","name":"LocalizationService","line":303,"character":73}]}],"ngOnInit":[{"__symbolic":"method"}],"ngOnChanges":[{"__symbolic":"method"}],"ngOnDestroy":[{"__symbolic":"method"}],"handleWrapperClick":[{"__symbolic":"method"}],"handleActiveColorClick":[{"__symbolic":"method"}],"focus":[{"__symbolic":"method"}],"handleWrapperFocus":[{"__symbolic":"method"}],"blur":[{"__symbolic":"method"}],"handleWrapperBlur":[{"__symbolic":"method"}],"reset":[{"__symbolic":"method"}],"toggle":[{"__symbolic":"method"}],"handleValueChange":[{"__symbolic":"method"}],"handlePopupBlur":[{"__symbolic":"method"}],"writeValue":[{"__symbolic":"method"}],"registerOnChange":[{"__symbolic":"method"}],"registerOnTouched":[{"__symbolic":"method"}],"setDisabledState":[{"__symbolic":"method"}],"handleWrapperKeyDown":[{"__symbolic":"method"}],"handlePopupKeyDown":[{"__symbolic":"method"}],"isEmpty":[{"__symbolic":"method"}],"toggleWithEvents":[{"__symbolic":"method"}],"openPopup":[{"__symbolic":"method"}],"closePopup":[{"__symbolic":"method"}]}},"ColorPaletteComponent":{"__symbolic":"class","decorators":[{"__symbolic":"call","expression":{"__symbolic":"reference","module":"@angular/core","name":"Component","line":33,"character":1},"arguments":[{"selector":"kendo-colorpalette","providers":[{"multi":true,"provide":{"__symbolic":"reference","module":"@angular/forms","name":"NG_VALUE_ACCESSOR","line":38,"character":21},"useExisting":{"__symbolic":"reference","name":"ColorPaletteComponent"}},{"provide":{"__symbolic":"reference","module":"@progress/kendo-angular-common","name":"KendoInput","line":41,"character":21},"useExisting":{"__symbolic":"reference","name":"ColorPaletteComponent"}},{"__symbolic":"reference","name":"ColorPaletteService"},{"__symbolic":"reference","module":"@progress/kendo-angular-l10n","name":"LocalizationService","line":45,"character":8},{"provide":{"__symbolic":"reference","module":"@progress/kendo-angular-l10n","name":"L10N_PREFIX","line":47,"character":21},"useValue":"kendo.colorpalette"}],"template":"\n        <div role=\"grid\">\n            <table class=\"k-palette k-reset\" role=\"presentation\">\n                <tbody>\n                    <tr role=\"row\" *ngFor=\"let row of colorRows; let rowIndex = index\">\n                        <td *ngFor=\"let color of row; let colIndex = index\"\n                            [class.k-state-selected]=\"focusedCell?.row === rowIndex && focusedCell?.col === colIndex\"\n                            class=\"k-item\"\n                            [attr.value]=\"color\"\n                            (click)=\"handleCellSelection(color, { row: rowIndex, col: colIndex })\"\n                            [ngStyle]=\"{\n                                backgroundColor: color,\n                                width: tileLayout.width + 'px',\n                                height: tileLayout.height + 'px',\n                                minWidth: tileLayout.width + 'px'\n                            }\">\n                        </td>\n                    </tr>\n                </tbody>\n            </table>\n        </div>\n    "}]}],"members":{"direction":[{"__symbolic":"property","decorators":[{"__symbolic":"call","expression":{"__symbolic":"reference","module":"@angular/core","name":"HostBinding","line":78,"character":5},"arguments":["attr.dir"]}]}],"format":[{"__symbolic":"property","decorators":[{"__symbolic":"call","expression":{"__symbolic":"reference","module":"@angular/core","name":"Input","line":90,"character":5}}]}],"value":[{"__symbolic":"property","decorators":[{"__symbolic":"call","expression":{"__symbolic":"reference","module":"@angular/core","name":"Input","line":95,"character":5}}]}],"columns":[{"__symbolic":"property","decorators":[{"__symbolic":"call","expression":{"__symbolic":"reference","module":"@angular/core","name":"Input","line":107,"character":5}}]}],"palette":[{"__symbolic":"property","decorators":[{"__symbolic":"call","expression":{"__symbolic":"reference","module":"@angular/core","name":"Input","line":124,"character":5}}]}],"tabindex":[{"__symbolic":"property","decorators":[{"__symbolic":"call","expression":{"__symbolic":"reference","module":"@angular/core","name":"Input","line":145,"character":5}}]}],"disabled":[{"__symbolic":"property","decorators":[{"__symbolic":"call","expression":{"__symbolic":"reference","module":"@angular/core","name":"Input","line":158,"character":5}}]}],"readonly":[{"__symbolic":"property","decorators":[{"__symbolic":"call","expression":{"__symbolic":"reference","module":"@angular/core","name":"Input","line":163,"character":5}}]}],"tileSize":[{"__symbolic":"property","decorators":[{"__symbolic":"call","expression":{"__symbolic":"reference","module":"@angular/core","name":"Input","line":172,"character":5}}]}],"selectionChange":[{"__symbolic":"property","decorators":[{"__symbolic":"call","expression":{"__symbolic":"reference","module":"@angular/core","name":"Output","line":188,"character":5}}]}],"valueChange":[{"__symbolic":"property","decorators":[{"__symbolic":"call","expression":{"__symbolic":"reference","module":"@angular/core","name":"Output","line":193,"character":5}}]}],"cellSelection":[{"__symbolic":"property","decorators":[{"__symbolic":"call","expression":{"__symbolic":"reference","module":"@angular/core","name":"Output","line":200,"character":5}}]}],"hostTabindex":[{"__symbolic":"property","decorators":[{"__symbolic":"call","expression":{"__symbolic":"reference","module":"@angular/core","name":"HostBinding","line":217,"character":5},"arguments":["attr.tabindex"]}]}],"hostClasses":[{"__symbolic":"property","decorators":[{"__symbolic":"call","expression":{"__symbolic":"reference","module":"@angular/core","name":"HostBinding","line":223,"character":5},"arguments":["class.k-widget"]},{"__symbolic":"call","expression":{"__symbolic":"reference","module":"@angular/core","name":"HostBinding","line":224,"character":5},"arguments":["class.k-colorpalette"]}]}],"disabledClass":[{"__symbolic":"property","decorators":[{"__symbolic":"call","expression":{"__symbolic":"reference","module":"@angular/core","name":"HostBinding","line":230,"character":5},"arguments":["class.k-state-disabled"]}]}],"__ctor__":[{"__symbolic":"constructor","parameters":[{"__symbolic":"reference","name":"ColorPaletteService"},{"__symbolic":"reference","module":"@progress/kendo-angular-l10n","name":"LocalizationService","line":243,"character":29}]}],"ngOnInit":[{"__symbolic":"method"}],"ngOnDestroy":[{"__symbolic":"method"}],"ngOnChanges":[{"__symbolic":"method"}],"handleKeydown":[{"__symbolic":"method","decorators":[{"__symbolic":"call","expression":{"__symbolic":"reference","module":"@angular/core","name":"HostListener","line":278,"character":5},"arguments":["keydown",["$event"]]}]}],"handleHostBlur":[{"__symbolic":"method","decorators":[{"__symbolic":"call","expression":{"__symbolic":"reference","module":"@angular/core","name":"HostListener","line":296,"character":5},"arguments":["blur"]}]}],"handleCellSelection":[{"__symbolic":"method"}],"writeValue":[{"__symbolic":"method"}],"registerOnChange":[{"__symbolic":"method"}],"registerOnTouched":[{"__symbolic":"method"}],"setDisabledState":[{"__symbolic":"method"}],"isEmpty":[{"__symbolic":"method"}],"reset":[{"__symbolic":"method"}],"setRows":[{"__symbolic":"method"}],"handleCellNavigation":[{"__symbolic":"method"}],"handleEnter":[{"__symbolic":"method"}]}},"ColorGradientComponent":{"__symbolic":"class","decorators":[{"__symbolic":"call","expression":{"__symbolic":"reference","module":"@angular/core","name":"Component","line":35,"character":1},"arguments":[{"selector":"kendo-colorgradient","providers":[{"multi":true,"provide":{"__symbolic":"reference","module":"@angular/forms","name":"NG_VALUE_ACCESSOR","line":39,"character":17},"useExisting":{"__symbolic":"reference","name":"ColorGradientComponent"}},{"provide":{"__symbolic":"reference","module":"@progress/kendo-angular-common","name":"KendoInput","line":42,"character":17},"useExisting":{"__symbolic":"reference","name":"ColorGradientComponent"}},{"__symbolic":"reference","module":"@progress/kendo-angular-l10n","name":"LocalizationService","line":45,"character":4},{"provide":{"__symbolic":"reference","module":"@progress/kendo-angular-l10n","name":"L10N_PREFIX","line":47,"character":21},"useValue":"kendo.colorgradient"}],"template":"\n        <div class=\"k-hbox k-hsv-wrap\">\n            <div class=\"k-hsv-rectangle\" [style.background-color]=\"backgroundColor\">\n                <div\n                    #gradientWrapper\n                    kendoDraggable\n                    class=\"k-hsv-gradient\"\n                    (click)=\"changePosition($event)\"\n                    (kendoPress)=\"handleDragPress($event)\"\n                    (kendoDrag)=\"onHandleDrag($event)\"\n                    (kendoRelease)=\"onHandleRelease()\">\n                    <div\n                        #dragHandle\n                        class=\"k-draghandle\"\n                    >\n                    </div>\n                </div>\n            </div>\n            <div class=\"k-hbox k-sliders-wrap {{ clearButton ? 'k-sliders-wrap-clearable' : '' }}\">\n                <span class=\"k-clear-color k-button k-bare k-button-icon\" *ngIf=\"clearButton\" (click)=\"reset()\">\n                    <span class=\"k-icon k-i-reset-color\"></span>\n                </span>\n                <kendo-slider\n                    class=\"k-hue-slider\"\n                    [disabled]=\"disabled\"\n                    [readonly]=\"readonly\"\n                    [showButtons]=\"false\"\n                    [tickPlacement]=\"'none'\"\n                    [vertical]=\"true\"\n                    [min]=\"0\"\n                    [max]=\"360\"\n                    [smallStep]=\"5\"\n                    [largeStep]=\"10\"\n                    [(value)]=\"hsva.h\"\n                    (valueChange)=\"handleHueSliderChange($event)\"\n                >\n                </kendo-slider>\n                <kendo-slider\n                    *ngIf=\"opacity && format === 'rgba'\"\n                    #alphaSlider\n                    class=\"k-alpha-slider\"\n                    [disabled]=\"disabled\"\n                    [readonly]=\"readonly\"\n                    [showButtons]=\"false\"\n                    [tickPlacement]=\"'none'\"\n                    [vertical]=\"true\"\n                    [min]=\"0\"\n                    [max]=\"100\"\n                    [smallStep]=\"1\"\n                    [largeStep]=\"10\"\n                    [value]=\"alphaSliderValue\"\n                    (valueChange)=\"handleAlphaSliderChange($event)\"\n                >\n                </kendo-slider>\n            </div>\n        </div>\n        <kendo-colorinput\n            [opacity]=\"opacity\"\n            [value]=\"value\"\n            [disabled]=\"disabled\"\n            [readonly]=\"readonly\"\n            (valueChange)=\"handleInputsValueChange($event)\"\n        >\n        </kendo-colorinput>\n"}]}],"members":{"hostClasses":[{"__symbolic":"property","decorators":[{"__symbolic":"call","expression":{"__symbolic":"reference","module":"@angular/core","name":"HostBinding","line":118,"character":5},"arguments":["class.k-widget"]},{"__symbolic":"call","expression":{"__symbolic":"reference","module":"@angular/core","name":"HostBinding","line":119,"character":5},"arguments":["class.k-flatcolorpicker"]}]}],"disabledClass":[{"__symbolic":"property","decorators":[{"__symbolic":"call","expression":{"__symbolic":"reference","module":"@angular/core","name":"HostBinding","line":122,"character":5},"arguments":["class.k-state-disabled"]}]}],"hostTabindex":[{"__symbolic":"property","decorators":[{"__symbolic":"call","expression":{"__symbolic":"reference","module":"@angular/core","name":"HostBinding","line":127,"character":5},"arguments":["attr.tabindex"]}]}],"direction":[{"__symbolic":"property","decorators":[{"__symbolic":"call","expression":{"__symbolic":"reference","module":"@angular/core","name":"HostBinding","line":135,"character":5},"arguments":["attr.dir"]}]}],"opacity":[{"__symbolic":"property","decorators":[{"__symbolic":"call","expression":{"__symbolic":"reference","module":"@angular/core","name":"Input","line":140,"character":5}}]}],"disabled":[{"__symbolic":"property","decorators":[{"__symbolic":"call","expression":{"__symbolic":"reference","module":"@angular/core","name":"Input","line":145,"character":5}}]}],"readonly":[{"__symbolic":"property","decorators":[{"__symbolic":"call","expression":{"__symbolic":"reference","module":"@angular/core","name":"Input","line":150,"character":5}}]}],"clearButton":[{"__symbolic":"property","decorators":[{"__symbolic":"call","expression":{"__symbolic":"reference","module":"@angular/core","name":"Input","line":155,"character":5}}]}],"value":[{"__symbolic":"property","decorators":[{"__symbolic":"call","expression":{"__symbolic":"reference","module":"@angular/core","name":"Input","line":159,"character":5}}]}],"tabindex":[{"__symbolic":"property","decorators":[{"__symbolic":"call","expression":{"__symbolic":"reference","module":"@angular/core","name":"Input","line":170,"character":5}}]}],"valueChange":[{"__symbolic":"property","decorators":[{"__symbolic":"call","expression":{"__symbolic":"reference","module":"@angular/core","name":"Output","line":183,"character":5}}]}],"format":[{"__symbolic":"property","decorators":[{"__symbolic":"call","expression":{"__symbolic":"reference","module":"@angular/core","name":"Input","line":231,"character":5}}]}],"alphaSlider":[{"__symbolic":"property","decorators":[{"__symbolic":"call","expression":{"__symbolic":"reference","module":"@angular/core","name":"ViewChild","line":239,"character":5},"arguments":["alphaSlider"]}]}],"gradientWrapper":[{"__symbolic":"property","decorators":[{"__symbolic":"call","expression":{"__symbolic":"reference","module":"@angular/core","name":"ViewChild","line":240,"character":5},"arguments":["gradientWrapper"]}]}],"dragHandle":[{"__symbolic":"property","decorators":[{"__symbolic":"call","expression":{"__symbolic":"reference","module":"@angular/core","name":"ViewChild","line":241,"character":5},"arguments":["dragHandle"]}]}],"__ctor__":[{"__symbolic":"constructor","parameters":[{"__symbolic":"reference","module":"@angular/core","name":"ElementRef","line":248,"character":22},{"__symbolic":"reference","module":"@angular/core","name":"NgZone","line":249,"character":24},{"__symbolic":"reference","module":"@angular/core","name":"Renderer2","line":250,"character":26},{"__symbolic":"reference","module":"@angular/core","name":"ChangeDetectorRef","line":251,"character":21},{"__symbolic":"reference","module":"@progress/kendo-angular-l10n","name":"LocalizationService","line":252,"character":29}]}],"ngAfterViewInit":[{"__symbolic":"method"}],"ngOnChanges":[{"__symbolic":"method"}],"ngOnDestroy":[{"__symbolic":"method"}],"focus":[{"__symbolic":"method"}],"reset":[{"__symbolic":"method"}],"handleDragPress":[{"__symbolic":"method"}],"onHandleDrag":[{"__symbolic":"method"}],"onHandleRelease":[{"__symbolic":"method"}],"changePosition":[{"__symbolic":"method"}],"handleHueSliderChange":[{"__symbolic":"method"}],"handleAlphaSliderChange":[{"__symbolic":"method"}],"handleInputsValueChange":[{"__symbolic":"method"}],"writeValue":[{"__symbolic":"method"}],"registerOnChange":[{"__symbolic":"method"}],"registerOnTouched":[{"__symbolic":"method"}],"setDisabledState":[{"__symbolic":"method"}],"isEmpty":[{"__symbolic":"method"}],"moveDragHandle":[{"__symbolic":"method"}],"updateUI":[{"__symbolic":"method"}],"handleValueChange":[{"__symbolic":"method"}],"setDragHandleElementPosition":[{"__symbolic":"method"}],"setAlphaSliderBackground":[{"__symbolic":"method"}],"addEventListeners":[{"__symbolic":"method"}]}},"ColorPickerModule":{"__symbolic":"class","decorators":[{"__symbolic":"call","expression":{"__symbolic":"reference","module":"@angular/core","name":"NgModule","line":29,"character":1},"arguments":[{"declarations":[[{"__symbolic":"reference","name":"ColorPickerComponent"},{"__symbolic":"reference","name":"ColorPaletteComponent"},{"__symbolic":"reference","name":"ColorGradientComponent"}],[{"__symbolic":"reference","name":"ColorInputComponent"},{"__symbolic":"reference","name":"FocusOnDomReadyDirective"}]],"exports":[[{"__symbolic":"reference","name":"ColorPickerComponent"},{"__symbolic":"reference","name":"ColorPaletteComponent"},{"__symbolic":"reference","name":"ColorGradientComponent"}]],"imports":[{"__symbolic":"reference","name":"SliderModule"},{"__symbolic":"reference","name":"NumericTextBoxModule"},{"__symbolic":"reference","module":"@angular/common","name":"CommonModule","line":38,"character":8},{"__symbolic":"reference","module":"@progress/kendo-angular-popup","name":"PopupModule","line":39,"character":8},{"__symbolic":"reference","module":"@progress/kendo-angular-common","name":"DraggableModule","line":40,"character":8}]}]}],"members":{}},"PopupSettings":{"__symbolic":"interface"},"TileSize":{"__symbolic":"interface"},"PaletteSettings":{"__symbolic":"interface"},"OutputFormat":{"__symbolic":"interface"},"ActiveColorClickEvent":{"__symbolic":"class","members":{"__ctor__":[{"__symbolic":"constructor","parameters":[{"__symbolic":"reference","name":"string"}]}],"preventOpen":[{"__symbolic":"method"}],"isOpenPrevented":[{"__symbolic":"method"}]}},"ColorPickerView":{"__symbolic":"interface"},"GradientSettings":{"__symbolic":"interface"},"Messages":{"__symbolic":"class","extends":{"__symbolic":"reference","module":"@progress/kendo-angular-l10n","name":"ComponentMessages","line":6,"character":30},"members":{"decrement":[{"__symbolic":"property","decorators":[{"__symbolic":"call","expression":{"__symbolic":"reference","module":"@angular/core","name":"Input","line":10,"character":5}}]}],"increment":[{"__symbolic":"property","decorators":[{"__symbolic":"call","expression":{"__symbolic":"reference","module":"@angular/core","name":"Input","line":15,"character":5}}]}]}},"MaskingService":{"__symbolic":"class","decorators":[{"__symbolic":"call","expression":{"__symbolic":"reference","module":"@angular/core","name":"Injectable","line":16,"character":1}}],"members":{"update":[{"__symbolic":"method"}],"validationValue":[{"__symbolic":"method"}],"rawValue":[{"__symbolic":"method"}],"maskRaw":[{"__symbolic":"method"}],"maskInput":[{"__symbolic":"method"}],"maskInRange":[{"__symbolic":"method"}],"maskRemoved":[{"__symbolic":"method"}],"adjustPosition":[{"__symbolic":"method"}],"maskInserted":[{"__symbolic":"method"}],"tokenize":[{"__symbolic":"method"}]}},"SliderCustomMessagesComponent":{"__symbolic":"class","extends":{"__symbolic":"reference","name":"Messages$1"},"decorators":[{"__symbolic":"call","expression":{"__symbolic":"reference","module":"@angular/core","name":"Component","line":7,"character":1},"arguments":[{"providers":[{"provide":{"__symbolic":"reference","name":"Messages$1"},"useExisting":{"__symbolic":"reference","name":"SliderCustomMessagesComponent"}}],"selector":"kendo-slider-messages","template":""}]}],"members":{"__ctor__":[{"__symbolic":"constructor","parameters":[{"__symbolic":"reference","module":"@progress/kendo-angular-l10n","name":"LocalizationService","line":18,"character":35}]}]}},"Messages$1":{"__symbolic":"class","extends":{"__symbolic":"reference","module":"@progress/kendo-angular-l10n","name":"ComponentMessages","line":6,"character":30},"members":{"decrement":[{"__symbolic":"property","decorators":[{"__symbolic":"call","expression":{"__symbolic":"reference","module":"@angular/core","name":"Input","line":10,"character":5}}]}],"increment":[{"__symbolic":"property","decorators":[{"__symbolic":"call","expression":{"__symbolic":"reference","module":"@angular/core","name":"Input","line":15,"character":5}}]}],"dragHandle":[{"__symbolic":"property","decorators":[{"__symbolic":"call","expression":{"__symbolic":"reference","module":"@angular/core","name":"Input","line":20,"character":5}}]}]}},"LocalizedMessagesDirective$1":{"__symbolic":"class","extends":{"__symbolic":"reference","name":"Messages$1"},"decorators":[{"__symbolic":"call","expression":{"__symbolic":"reference","module":"@angular/core","name":"Directive","line":7,"character":1},"arguments":[{"providers":[{"provide":{"__symbolic":"reference","name":"Messages$1"},"useExisting":{"__symbolic":"reference","name":"LocalizedMessagesDirective$1"}}],"selector":"[kendoSliderLocalizedMessages]"}]}],"members":{"__ctor__":[{"__symbolic":"constructor","parameters":[{"__symbolic":"reference","module":"@progress/kendo-angular-l10n","name":"LocalizationService","line":17,"character":35}]}]}},"SwitchCustomMessagesComponent":{"__symbolic":"class","extends":{"__symbolic":"reference","name":"Messages$2"},"decorators":[{"__symbolic":"call","expression":{"__symbolic":"reference","module":"@angular/core","name":"Component","line":7,"character":1},"arguments":[{"providers":[{"provide":{"__symbolic":"reference","name":"Messages$2"},"useExisting":{"__symbolic":"reference","name":"SwitchCustomMessagesComponent"}}],"selector":"kendo-switch-messages","template":""}]}],"members":{"__ctor__":[{"__symbolic":"constructor","parameters":[{"__symbolic":"reference","module":"@progress/kendo-angular-l10n","name":"LocalizationService","line":18,"character":35}]}]}},"Messages$2":{"__symbolic":"class","extends":{"__symbolic":"reference","module":"@progress/kendo-angular-l10n","name":"ComponentMessages","line":6,"character":30},"members":{"on":[{"__symbolic":"property","decorators":[{"__symbolic":"call","expression":{"__symbolic":"reference","module":"@angular/core","name":"Input","line":10,"character":5}}]}],"off":[{"__symbolic":"property","decorators":[{"__symbolic":"call","expression":{"__symbolic":"reference","module":"@angular/core","name":"Input","line":15,"character":5}}]}]}},"LocalizedMessagesDirective$2":{"__symbolic":"class","extends":{"__symbolic":"reference","name":"Messages$2"},"decorators":[{"__symbolic":"call","expression":{"__symbolic":"reference","module":"@angular/core","name":"Directive","line":7,"character":1},"arguments":[{"providers":[{"provide":{"__symbolic":"reference","name":"Messages$2"},"useExisting":{"__symbolic":"reference","name":"LocalizedMessagesDirective$2"}}],"selector":"[kendoSwitchLocalizedMessages]"}]}],"members":{"__ctor__":[{"__symbolic":"constructor","parameters":[{"__symbolic":"reference","module":"@progress/kendo-angular-l10n","name":"LocalizationService","line":17,"character":35}]}]}},"LocalizedMessagesDirective":{"__symbolic":"class","extends":{"__symbolic":"reference","name":"Messages"},"decorators":[{"__symbolic":"call","expression":{"__symbolic":"reference","module":"@angular/core","name":"Directive","line":7,"character":1},"arguments":[{"providers":[{"provide":{"__symbolic":"reference","name":"Messages"},"useExisting":{"__symbolic":"reference","name":"LocalizedMessagesDirective"}}],"selector":"[kendoNumericTextBoxLocalizedMessages]"}]}],"members":{"__ctor__":[{"__symbolic":"constructor","parameters":[{"__symbolic":"reference","module":"@progress/kendo-angular-l10n","name":"LocalizationService","line":17,"character":35}]}]}},"ColorPaletteService":{"__symbolic":"class","decorators":[{"__symbolic":"call","expression":{"__symbolic":"reference","module":"@angular/core","name":"Injectable","line":8,"character":1}}],"members":{"setColorMatrix":[{"__symbolic":"method"}],"getCellCoordsFor":[{"__symbolic":"method"}],"getColorAt":[{"__symbolic":"method"}],"getNextCell":[{"__symbolic":"method"}],"clampIndex":[{"__symbolic":"method"}]}},"ColorInputComponent":{"__symbolic":"class","decorators":[{"__symbolic":"call","expression":{"__symbolic":"reference","module":"@angular/core","name":"Component","line":19,"character":1},"arguments":[{"selector":"kendo-colorinput","template":"\n        <div class=\"k-hbox k-gradient-values\">\n            <input\n                #hexInput\n                class=\"k-textbox k-hex-value\"\n                [disabled]=\"disabled\"\n                [readonly]=\"readonly\"\n                [value]=\"hex || ''\"\n                placeholder=\"no color\"\n                (blur)=\"handleHexInputBlur()\"\n                (input)=\"handleHexValueChange(hexInput.value)\"\n            />\n            <kendo-numerictextbox\n                [disabled]=\"disabled\"\n                [readonly]=\"readonly\"\n                [min]=\"0\"\n                [max]=\"255\"\n                placeholder=\"R\"\n                [(value)]=\"rgba.r\"\n                [autoCorrect]=\"true\"\n                [spinners]=\"false\"\n                [format]=\"'n'\"\n                [decimals]=\"0\"\n                (blur)=\"handleRgbaInputBlur()\"\n                (valueChange)=\"handleRgbaValueChange()\"\n            >\n            </kendo-numerictextbox>\n            <kendo-numerictextbox\n                [disabled]=\"disabled\"\n                [readonly]=\"readonly\"\n                [min]=\"0\"\n                [max]=\"255\"\n                placeholder=\"G\"\n                [(value)]=\"rgba.g\"\n                [autoCorrect]=\"true\"\n                [spinners]=\"false\"\n                [format]=\"'n'\"\n                [decimals]=\"0\"\n                (blur)=\"handleRgbaInputBlur()\"\n                (valueChange)=\"handleRgbaValueChange()\"\n            >\n            </kendo-numerictextbox>\n            <kendo-numerictextbox\n                [disabled]=\"disabled\"\n                [readonly]=\"readonly\"\n                [min]=\"0\"\n                [max]=\"255\"\n                placeholder=\"B\"\n                [(value)]=\"rgba.b\"\n                [autoCorrect]=\"true\"\n                [spinners]=\"false\"\n                [format]=\"'n'\"\n                [decimals]=\"0\"\n                (blur)=\"handleRgbaInputBlur()\"\n                (valueChange)=\"handleRgbaValueChange()\"\n            >\n            </kendo-numerictextbox>\n            <kendo-numerictextbox\n                *ngIf=\"opacity\"\n                [disabled]=\"disabled\"\n                [readonly]=\"readonly\"\n                [min]=\"0\"\n                [max]=\"1\"\n                placeholder=\"A\"\n                [(value)]=\"rgba.a\"\n                [autoCorrect]=\"true\"\n                [spinners]=\"false\"\n                [step]=\"0.01\"\n                [format]=\"'n2'\"\n                [decimals]=\"2\"\n                (blur)=\"handleRgbaInputBlur()\"\n                (valueChange)=\"handleRgbaValueChange()\"\n            >\n            </kendo-numerictextbox>\n        </div>\n        <div class=\"k-hbox k-gradient-values\">\n            <div class=\"k-hex-value\">hex</div>\n            <div>r</div>\n            <div>g</div>\n            <div>b</div>\n            <div *ngIf=\"opacity\">a</div>\n        </div>\n    "}]}],"members":{"value":[{"__symbolic":"property","decorators":[{"__symbolic":"call","expression":{"__symbolic":"reference","module":"@angular/core","name":"Input","line":110,"character":5}}]}],"opacity":[{"__symbolic":"property","decorators":[{"__symbolic":"call","expression":{"__symbolic":"reference","module":"@angular/core","name":"Input","line":115,"character":5}}]}],"disabled":[{"__symbolic":"property","decorators":[{"__symbolic":"call","expression":{"__symbolic":"reference","module":"@angular/core","name":"Input","line":120,"character":5}}]}],"readonly":[{"__symbolic":"property","decorators":[{"__symbolic":"call","expression":{"__symbolic":"reference","module":"@angular/core","name":"Input","line":125,"character":5}}]}],"valueChange":[{"__symbolic":"property","decorators":[{"__symbolic":"call","expression":{"__symbolic":"reference","module":"@angular/core","name":"Output","line":130,"character":5}}]}],"colorInputClass":[{"__symbolic":"property","decorators":[{"__symbolic":"call","expression":{"__symbolic":"reference","module":"@angular/core","name":"HostBinding","line":132,"character":5},"arguments":["class.k-colorinputs"]}]}],"__ctor__":[{"__symbolic":"constructor","parameters":[{"__symbolic":"reference","module":"@angular/core","name":"ElementRef","line":163,"character":30}]}],"ngOnChanges":[{"__symbolic":"method"}],"handleRgbaValueChange":[{"__symbolic":"method"}],"handleHexValueChange":[{"__symbolic":"method"}],"handleRgbaInputBlur":[{"__symbolic":"method"}],"handleHexInputBlur":[{"__symbolic":"method"}]}},"FocusOnDomReadyDirective":{"__symbolic":"class","decorators":[{"__symbolic":"call","expression":{"__symbolic":"reference","module":"@angular/core","name":"Directive","line":5,"character":1},"arguments":[{"selector":"[kendoFocusOnDomReady]"}]}],"members":{"__ctor__":[{"__symbolic":"constructor","parameters":[{"__symbolic":"reference","module":"@angular/core","name":"ElementRef","line":10,"character":22},{"__symbolic":"reference","module":"@angular/core","name":"NgZone","line":11,"character":24}]}],"ngAfterContentInit":[{"__symbolic":"method"}],"focusOnNextTick":[{"__symbolic":"method"}]}}},"origins":{"SliderComponent":"./slider/slider.component","LabelTemplateDirective":"./slider/label-template.directive","SwitchComponent":"./switch/switch.component","TextBoxContainerComponent":"./textbox/textbox-container.component","TextBoxDirective":"./textbox/textbox.directive","TextAreaDirective":"./textbox/textarea.directive","NumericTextBoxComponent":"./numerictextbox/numerictextbox.component","NumericTextBoxCustomMessagesComponent":"./numerictextbox/localization/custom-messages.component","MaskedTextBoxComponent":"./maskedtextbox/maskedtextbox.component","InputsModule":"./inputs.module","SliderTicksComponent":"./slider/slider-ticks.component","SliderModule":"./slider.module","SwitchModule":"./switch.module","NumericTextBoxModule":"./numerictextbox.module","MaskedTextBoxModule":"./maskedtextbox.module","TextBoxModule":"./textbox.module","ColorPickerComponent":"./colorpicker/colorpicker.component","ColorPaletteComponent":"./colorpicker/color-palette.component","ColorGradientComponent":"./colorpicker/color-gradient.component","ColorPickerModule":"./colorpicker.module","PopupSettings":"./colorpicker/models/popup-settings","TileSize":"./colorpicker/models/tile-size","PaletteSettings":"./colorpicker/models/palette-settings","OutputFormat":"./colorpicker/models/output-format","ActiveColorClickEvent":"./colorpicker/models/active-color-click-event","ColorPickerView":"./colorpicker/models/color-picker-view","GradientSettings":"./colorpicker/models/gradient-settings","Messages":"./numerictextbox/localization/messages","MaskingService":"./maskedtextbox/masking.service","SliderCustomMessagesComponent":"./slider/localization/custom-messages.component","Messages$1":"./slider/localization/messages","LocalizedMessagesDirective$1":"./slider/localization/localized-messages.directive","SwitchCustomMessagesComponent":"./switch/localization/custom-messages.component","Messages$2":"./switch/localization/messages","LocalizedMessagesDirective$2":"./switch/localization/localized-messages.directive","LocalizedMessagesDirective":"./numerictextbox/localization/localized-messages.directive","ColorPaletteService":"./colorpicker/services/color-palette.service","ColorInputComponent":"./colorpicker/color-input.component","FocusOnDomReadyDirective":"./colorpicker/focus-on-dom-ready.directive"},"importAs":"@progress/kendo-angular-inputs"}